Workbook

Sheet Por familia
A1: Dónde se DESARROLLA matemáticamente cada modelo (original y variantes)
A2: Solo cuentan desarrollos formales (al menos un bloque de ecuaciones atribuible al modelo); las menciones no cuentan. Las columnas numéricas son fórmulas sobre la hoja "Desarrollos". Una familia con ≥2 temas es candidata a homogeneizar.
A4: Área | B4: Familia (modelo original) | C4: Referencia | D4: Temas: versión original | E4: Temas: variantes (forma → tema) | F4: Nº temas distintos | G4: Nº desarrollos (filas) | H4: Nº completos | I4: ¿Duplicidad?
A5: Microeconomía | B5: Descuento cuasi-hiperbólico | C5: Laibson (1997) | D5: 3.A.29 | E5: — | F5: =SUMPRODUCT((Desarrollos!$B$2:$B$181=B5)/COUNTIFS(Desarrollos!$B$2:$B$181,Desarrollos!$B$2:$B$181,Desarrollos!$F$2:$F$181,Desarrollos!$F$2:$F$181)) -> 1 | G5: =COUNTIF(Desarrollos!$B$2:$B$181,B5) -> 1 | H5: =COUNTIFS(Desarrollos!$B$2:$B$181,B5,Desarrollos!$I$2:$I$181,">=4") -> 0 | I5: =IF(F5>=2,"Sí","No") -> No
A6: Microeconomía | B6: Asignación del tiempo | C6: Becker (1965) | D6: 3.A.25 | E6: — | F6: =SUMPRODUCT((Desarrollos!$B$2:$B$181=B6)/COUNTIFS(Desarrollos!$B$2:$B$181,Desarrollos!$B$2:$B$181,Desarrollos!$F$2:$F$181,Desarrollos!$F$2:$F$181)) -> 1 | G6: =COUNTIF(Desarrollos!$B$2:$B$181,B6) -> 1 | H6: =COUNTIFS(Desarrollos!$B$2:$B$181,B6,Desarrollos!$I$2:$I$181,">=4") -> 0 | I6: =IF(F6>=2,"Sí","No") -> No
A7: Microeconomía | B7: Elección ocio-consumo (oferta de trabajo neoclásica) | C7: Robbins (1930) / tradición neoclásica | D7: 3.A.6, 3.A.25 | E7: Oferta intertemporal de trabajo (Lucas-Rapping 1969) → 3.A.25 | F7: =SUMPRODUCT((Desarrollos!$B$2:$B$181=B7)/COUNTIFS(Desarrollos!$B$2:$B$181,Desarrollos!$B$2:$B$181,Desarrollos!$F$2:$F$181,Desarrollos!$F$2:$F$181)) -> 2 | G7: =COUNTIF(Desarrollos!$B$2:$B$181,B7) -> 3 | H7: =COUNTIFS(Desarrollos!$B$2:$B$181,B7,Desarrollos!$I$2:$I$181,">=4") -> 2 | I7: =IF(F7>=2,"Sí","No") -> Sí
A8: Microeconomía | B8: Competencia monopolística | C8: Chamberlin (1933) | D8: — (solo variantes) | E8: Dixit-Stiglitz (1977) → 3.A.18, 3.B.6 | F8: =SUMPRODUCT((Desarrollos!$B$2:$B$181=B8)/COUNTIFS(Desarrollos!$B$2:$B$181,Desarrollos!$B$2:$B$181,Desarrollos!$F$2:$F$181,Desarrollos!$F$2:$F$181)) -> 2 | G8: =COUNTIF(Desarrollos!$B$2:$B$181,B8) -> 2 | H8: =COUNTIFS(Desarrollos!$B$2:$B$181,B8,Desarrollos!$I$2:$I$181,">=4") -> 1 | I8: =IF(F8>=2,"Sí","No") -> Sí
A9: Microeconomía | B9: Duopolio de Cournot | C9: Cournot (1838) | D9: 3.A.19 | E9: Variaciones conjeturales (Bowley 1924) → 3.A.19 | F9: =SUMPRODUCT((Desarrollos!$B$2:$B$181=B9)/COUNTIFS(Desarrollos!$B$2:$B$181,Desarrollos!$B$2:$B$181,Desarrollos!$F$2:$F$181,Desarrollos!$F$2:$F$181)) -> 1 | G9: =COUNTIF(Desarrollos!$B$2:$B$181,B9) -> 2 | H9: =COUNTIFS(Desarrollos!$B$2:$B$181,B9,Desarrollos!$I$2:$I$181,">=4") -> 1 | I9: =IF(F9>=2,"Sí","No") -> No
A10: Microeconomía | B10: Duopolio de Bertrand | C10: Bertrand (1883) | D10: 3.A.19 | E10: — | F10: =SUMPRODUCT((Desarrollos!$B$2:$B$181=B10)/COUNTIFS(Desarrollos!$B$2:$B$181,Desarrollos!$B$2:$B$181,Desarrollos!$F$2:$F$181,Desarrollos!$F$2:$F$181)) -> 1 | G10: =COUNTIF(Desarrollos!$B$2:$B$181,B10) -> 1 | H10: =COUNTIFS(Desarrollos!$B$2:$B$181,B10,Desarrollos!$I$2:$I$181,">=4") -> 0 | I10: =IF(F10>=2,"Sí","No") -> No
A11: Microeconomía | B11: Ciudad lineal (diferenciación espacial) | C11: Hotelling (1929) | D11: 3.A.18 | E11: Ciudad circular (Salop 1979) → 3.A.18 | F11: =SUMPRODUCT((Desarrollos!$B$2:$B$181=B11)/COUNTIFS(Desarrollos!$B$2:$B$181,Desarrollos!$B$2:$B$181,Desarrollos!$F$2:$F$181,Desarrollos!$F$2:$F$181)) -> 1 | G11: =COUNTIF(Desarrollos!$B$2:$B$181,B11) -> 2 | H11: =COUNTIFS(Desarrollos!$B$2:$B$181,B11,Desarrollos!$I$2:$I$181,">=4") -> 0 | I11: =IF(F11>=2,"Sí","No") -> No
A12: Microeconomía | B12: Principal-agente | C12: Ross (1973) / Jensen-Meckling (1976) | D12: 3.A.13 | E12: Holmström (1979) — condiciones de primer orden → 3.A.13 | F12: =SUMPRODUCT((Desarrollos!$B$2:$B$181=B12)/COUNTIFS(Desarrollos!$B$2:$B$181,Desarrollos!$B$2:$B$181,Desarrollos!$F$2:$F$181,Desarrollos!$F$2:$F$181)) -> 1 | G12: =COUNTIF(Desarrollos!$B$2:$B$181,B12) -> 2 | H12: =COUNTIFS(Desarrollos!$B$2:$B$181,B12,Desarrollos!$I$2:$I$181,">=4") -> 1 | I12: =IF(F12>=2,"Sí","No") -> No
A13: Microeconomía | B13: Filtrado en mercado de seguros | C13: Rothschild-Stiglitz (1976) | D13: — (solo variantes) | E13: Screening monopolístico (Mussa-Rosen 1978) → 3.A.13 | F13: =SUMPRODUCT((Desarrollos!$B$2:$B$181=B13)/COUNTIFS(Desarrollos!$B$2:$B$181,Desarrollos!$B$2:$B$181,Desarrollos!$F$2:$F$181,Desarrollos!$F$2:$F$181)) -> 1 | G13: =COUNTIF(Desarrollos!$B$2:$B$181,B13) -> 1 | H13: =COUNTIFS(Desarrollos!$B$2:$B$181,B13,Desarrollos!$I$2:$I$181,">=4") -> 0 | I13: =IF(F13>=2,"Sí","No") -> No
A14: Microeconomía | B14: Señalización en el mercado de trabajo | C14: Spence (1973) | D14: 3.A.13 | E14: Señalización financiera (Ross 1977) → 3.B.3 | F14: =SUMPRODUCT((Desarrollos!$B$2:$B$181=B14)/COUNTIFS(Desarrollos!$B$2:$B$181,Desarrollos!$B$2:$B$181,Desarrollos!$F$2:$F$181,Desarrollos!$F$2:$F$181)) -> 2 | G14: =COUNTIF(Desarrollos!$B$2:$B$181,B14) -> 2 | H14: =COUNTIFS(Desarrollos!$B$2:$B$181,B14,Desarrollos!$I$2:$I$181,">=4") -> 0 | I14: =IF(F14>=2,"Sí","No") -> Sí
A15: Microeconomía | B15: Equilibrio general walrasiano / Arrow-Debreu | C15: Walras (1874) / Arrow-Debreu (1954) | D15: 3.A.16, 3.A.21 | E15: Equilibrio de Radner (1972) → 3.A.21 | F15: =SUMPRODUCT((Desarrollos!$B$2:$B$181=B15)/COUNTIFS(Desarrollos!$B$2:$B$181,Desarrollos!$B$2:$B$181,Desarrollos!$F$2:$F$181,Desarrollos!$F$2:$F$181)) -> 2 | G15: =COUNTIF(Desarrollos!$B$2:$B$181,B15) -> 3 | H15: =COUNTIFS(Desarrollos!$B$2:$B$181,B15,Desarrollos!$I$2:$I$181,">=4") -> 2 | I15: =IF(F15>=2,"Sí","No") -> Sí
A16: Microeconomía | B16: Tablas input-output | C16: Leontief (1936) | D16: 3.A.31 | E16: — | F16: =SUMPRODUCT((Desarrollos!$B$2:$B$181=B16)/COUNTIFS(Desarrollos!$B$2:$B$181,Desarrollos!$B$2:$B$181,Desarrollos!$F$2:$F$181,Desarrollos!$F$2:$F$181)) -> 1 | G16: =COUNTIF(Desarrollos!$B$2:$B$181,B16) -> 1 | H16: =COUNTIFS(Desarrollos!$B$2:$B$181,B16,Desarrollos!$I$2:$I$181,">=4") -> 0 | I16: =IF(F16>=2,"Sí","No") -> No
... A100: Finanzas | B100: Pérdida esperada e inesperada (IRB / Vasicek ASRF) | C100: Vasicek (2002) / Basilea II | D100: 3.B.26, 3.B.27 | E100: — | F100: =SUMPRODUCT((Desarrollos!$B$2:$B$181=B100)/COUNTIFS(Desarrollos!$B$2:$B$181,Desarrollos!$B$2:$B$181,Desarrollos!$F$2:$F$181,Desarrollos!$F$2:$F$181)) -> 2 | G100: =COUNTIF(Desarrollos!$B$2:$B$181,B100) -> 2 | H100: =COUNTIFS(Desarrollos!$B$2:$B$181,B100,Desarrollos!$I$2:$I$181,">=4") -> 0 | I100: =IF(F100>=2,"Sí","No") -> Sí

Sheet Duplicidades
A1: Familia (modelo original) | B1: Tema | C1: Título del tema | D1: Forma desarrollada | E1: Epígrafe(s) | F1: Nº bloques | G1: Grado
A2: Elección ocio-consumo (oferta de trabajo neoclásica) | B2: 3.A.6 | C2: La nueva macroeconomía clásica | D2: Versión original | E2: Modelo: Optimizacion intertemporal Ocio-Consumo | F2: 1 | G2: Parcial
B3: 3.A.25 | C3: La teoría neoclásica del mercado de trabajo | D3: Versión original | E3: El problema del consumidor: Eleccion entre consumo y ocio | Variaciones en la Funcion de Oferta Marshalliana | F3: 4 | G3: Completo
B4: 3.A.25 | C4: La teoría neoclásica del mercado de trabajo | D4: Oferta intertemporal de trabajo (Lucas-Rapping 1969) | E4: Obtencion de la oferta intertemporal de trabajo | F4: 4 | G4: Completo
A5: Competencia monopolística | B5: 3.A.18 | C5: Análisis de mercados (III) | D5: Dixit-Stiglitz (1977) | E5: Consumidor: Preferencia por la variedad | Condicion CES: Simplificacion | Elasticidades-renta unitarias | Elasticidad-precio de la demanda de una variedad | Elasticidad de sustitucion: Intersectorial e Intrasectorial | Indice de precios: Deflactor del bienestar | Productor: Competencia monopolistica | Condicion de libre entrada | F5: 9 | G5: Completo
B6: 3.B.6 | C6: Teoría del Comercio Internacional (II) | D6: Dixit-Stiglitz (1977) | E6: Demanda: CES-isoelastica | Productor: Simetria en costes | F6: 3 | G6: Parcial
A7: Señalización en el mercado de trabajo | B7: 3.A.13 | C7: Economía de la información | D7: Versión original | E7: Equilibrios agrupadores (pooling) | Ejemplo.- Educacion (SPENCE, 1973) | F7: 2 | G7: Parcial
B8: 3.B.3 | C8: La empresa y las decisiones de financiación | D8: Señalización financiera (Ross 1977) | E8: Senalizacion y control: ROSS (1977) | F8: 1 | G8: Parcial
A9: Equilibrio general walrasiano / Arrow-Debreu | B9: 3.A.16 | C9: Análisis de mercados (I) | D9: Versión original | E9: Tationnement: Subastador walrasiano | F9: 2 | G9: Parcial
B10: 3.A.21 | C10: La Teoría del Equilibrio General | D10: Versión original | E10: Funcion de Exceso de Demanda Agregada | Ley de WALRAS | Tatonnement en precios: General y reforzado | Informacion simetrica: Mercado de activos | Teoria del Equilibrio General (produccion): ARROW-DEBREU | F10: 9 | G10: Completo
B11: 3.A.21 | C11: La Teoría del Equilibrio General | D11: Equilibrio de Radner (1972) | E11: Equilibrio de RADNER | Desarrollo formal | Teoria del Equilibrio General: Modelo de comercio secuancial (RADNER) | F11: 4 | G11: Completo
A12: Imposición / tarificación óptima de Ramsey | B12: 4.B.11 | C12: Teoría impositiva (V): Imposición óptima | D12: Versión original | E12: Base general: | La regla de RAMSEY | Una reinterpretacion de la regla de RAMSEY: Regla de la elasticidad inversa | F12: 5 | G12: Completo
B13: 3.A.20 | C13: Regulación y Poder de mercado | D13: Ramsey-Boiteux (1956) | E13: Precios RAMSEY-BOITEAUX | F13: 1 | G13: Parcial
A14: Imposición óptima sobre la renta | B14: 4.B.11 | C14: Teoría impositiva (V): Imposición óptima | D14: Versión original | E14: Impuesto sobre la Renta Personal: Desarrollo analitico (MIRRLESS, 1971) | F14: 1 | G14: Parcial
B15: 4.B.10 | C15: Teoría impositiva (IV): Imposición y oferta | D15: Impuesto lineal óptimo (Stern 1976) | E15: Efecto incentivo al trabajo: Endogeneidad de la renta (STERN, 1987) | F15: 1 | G15: Parcial
A16: Modelo keynesiano simple (renta-gasto / aspa keynesiana) | B16: 3.A.38 | C16: Política Fiscal | D16: Versión original | E16: Politica fiscal: Gasto e Impuestos | F16: 1 | G16: Parcial
B17: 3.A.40 | C17: Efectividad e interrelación de las Políticas Monetarias y Fiscales | D17: Versión original | E17: Multiplicador Fiscal: Modelo keynesiano basico | Interrelacion con la Politica Monetaria: Tipo de Interes | Estabilizadores automaticos: Balance estructural | F17: 3 | G17: Parcial
B18: 3.B.14 | C18: Teorías de la determinación del Tipo de Cambio | D18: Versión original | E18: Desarrollo formal: el Aspa Keynesiana | F18: 1 | G18: Parcial
B19: 3.A.4 | C19: El pensamiento económico de KEYNES | D19: Sistema keynesiano completo (Teoría General) | E19: Determinantes de la inversion: Incentivo a invertir | Efecto del atesoramiento | F19: 2 | G19: Parcial
A20: IS-LM | B20: 3.A.5 | C20: La síntesis neoclásica | D20: Versión original | E20: Primeros planteamientos | Economia cerrada | Economia abierta | F20: 4 | G20: Completo
B21: 3.A.38 | C21: Política Fiscal | D21: Versión original | E21: Politica Fiscal: Teoria | F21: 2 | G21: Parcial
B22: 3.A.40 | C22: Efectividad e interrelación de las Políticas Monetarias y Fiscales | D22: Versión original | E22: Interrelacion con la Politica Monetaria: Tipo de Interes | F22: 1 | G22: Parcial
B23: 3.A.39 | C23: Déficit Público | D23: Blinder-Solow (1973) | E23: Revision de BLINDER y SOLOW (1973): SNC final | F23: 1 | G23: Parcial
A24: Inconsistencia temporal de la política | B24: 3.A.6 | C24: La nueva macroeconomía clásica | D24: Versión original | E24: Funcion de Perdida Social | F24: 1 | G24: Parcial
B25: 3.A.23 | C25: Economía del Bienestar (II) | D25: Versión original | E25: Modelo de Deficit Publico: Problemas de Inconsistencia Dinamica | F25: 2 | G25: Parcial
A26: Islas de Lucas (información imperfecta) | B26: 3.A.6 | C26: La nueva macroeconomía clásica | D26: Versión original | E26: Supuestos | Actualizacion de las expectativas y reaccion | Funcion de Oferta Agregada de LUCAS: Reaccion conjunta | Curvas de Oferta y Demanda Agregada. LUCAS | F26: 15 | G26: Completo
B27: 3.A.42 | C27: Teorías de los ciclos económicos | D27: Versión original | E27: Ciclos nominales: Curva de Oferta de LUCAS | F27: 2 | G27: Parcial
A28: Nuevo keynesiano de tres ecuaciones (NEK-2) | B28: 3.A.7 | C28: La nueva economía Keynesiana | D28: Versión original | E28: Curva IS ampliada por expectativas | Curva de PHILLIPS de la NEK | Modificaciones: Curvas de PHILLIPS hibridas | Regla de TAYLOR: Autoridad monetaria | Deseabilidad del Equilibrio: Principio de TAYLOR | Deseabilidad del Equilibrio | F28: 7 | G28: Completo
B29: 3.A.28 | C29: La tasa natural de paro y de la NAIRU | D29: Versión original | E29: Hogares | Los flujos en el mercado de trabajo | Empresa | Determinacion de salarios | Persistencia del desempelo: NEK-2 | Inflacion y desempleo | Perturbaciones macroeconomicas | F29: 12 | G29: Completo
B30: 3.A.37 | C30: Política Monetaria (II) | D30: Versión original | E30: La cuantificacion de sus efectos: modelo de la NEK-2 | F30: 1 | G30: Parcial
B31: 3.A.41 | C31: La inflación | D31: Versión original | E31: Shocks de oferta: Marco NEK-2 | Modelo NEK-2: ZLB y forward-guidance | NEK-2: Efectos sobre la Eficiencia y el Bienestar | Implicaciones de Politica Economica | F31: 4 | G31: Completo
B32: 3.A.42 | C32: Teorías de los ciclos económicos | D32: Versión original | E32: Modelo canonico: Derivacion analitica | Regla de Taylor: Autoridad Monetaria | ¿Divina Coincidencia? Politica Monetaria y Shocks | F32: 3 | G32: Parcial
A33: Renta permanente | B33: 3.A.5 | C33: La síntesis neoclásica | D33: Versión original | E33: Renta permanente | F33: 3 | G33: Parcial
B34: 3.A.29 | C34: Modelización dinámica de las tomas de decisiones | D34: Versión original | E34: Variaciones en la renta ( w ) | F34: 1 | G34: Parcial
B35: 3.A.33 | C35: Teorías de la demanda de consumo corriente | D35: Versión original | E35: Hipotesis de la Renta Permanente: FRIEDMAN | F35: 2 | G35: Parcial
B36: 3.A.33 | C36: Teorías de la demanda de consumo corriente | D36: Paseo aleatorio del consumo (Hall 1978) | E36: Paseo aleatorio: HALL | Limitaciones: Contrastacion Empirica | F36: 4 | G36: Completo
A37: Opciones reales de inversión | B37: 3.A.34 | C37: Teorías de la inversión en bienes de equipo | D37: Versión original | E37: Opciones reales: McDONALD y SIEGEL (1986) | F37: 1 | G37: Parcial
B38: 3.B.2 | C38: La empresa y las decisiones de inversión | D38: Versión original | E38: Incertidumbre: Opciones reales | F38: 1 | G38: Parcial
A39: Salarios de eficiencia | B39: 3.A.7 | C39: La nueva economía Keynesiana | D39: Versión original | E39: Mercado de trabajo | F39: 1 | G39: Parcial
B40: 3.A.27 | C40: Determinación de salarios | D40: Versión original | E40: Trabajo germinal: SOLOW | F40: 1 | G40: Parcial
B41: 3.A.27 | C41: Determinación de salarios | D41: Shapiro-Stiglitz (1984) | E41: Modelo de referencia: SHAPIRO-STIGLITZ | Equilibrio: Condicion de no-escaqueo | F41: 2 | G41: Parcial
A42: Búsqueda y emparejamiento (DMP) | B42: 3.A.26 | C42: Extensiones a la Teoría del Mercado de Trabajo | D42: Versión original | E42: Modelo baseline -- MORTENSEN, 1970 | Funcion de emparejamiento | Equilibrio estacionario | Condicion del trabajador: salario de reserva | Condicion de creacion de empleo: Producto | Equilibrio negociador: Fijacion del salario | F42: 10 | G42: Completo
B43: 3.A.28 | C43: La tasa natural de paro y de la NAIRU | D43: Versión original | E43: Desempleo friccional: Enfoque parcial. Modelo DPM | F43: 2 | G43: Parcial
A44: NAIRU / WS-PS | B44: 3.A.28 | C44: La tasa natural de paro y de la NAIRU | D44: Versión original | E44: Curva salarial | Fijacion de precios | F44: 2 | G44: Parcial
B45: 3.A.41 | C45: La inflación | D45: Versión original | E45: Curva salarial: Sindicatos | Fijacion de precios: Empresas | F45: 2 | G45: Parcial
A46: Ramsey-Cass-Koopmans | B46: 3.A.29 | C46: Modelización dinámica de las tomas de decisiones | D46: Versión original | E46: Optimizacion de los Hogares | Optimizacion de las Empresas | Equilibrio | F46: 4 | G46: Completo
B47: 3.A.43 | C47: Teorías del crecimiento económico (I) | D47: Versión original | E47: Desarrollo analitico | Estado Estacionario | Analisis normativo | F47: 3 | G47: Parcial
A48: Generaciones solapadas | B48: 3.A.29 | C48: Modelización dinámica de las tomas de decisiones | D48: Versión original | E48: Heterogeneidad de agentes | Ejemplo: Economia de intercambio puro | F48: 4 | G48: Completo
B49: 3.A.35 | C49: Teorías de la demanda de dinero | D49: Versión original | E49: Modelo MGS: Economia pura de intercambio | F49: 2 | G49: Parcial
B50: 3.A.38 | C50: Política Fiscal | D50: Versión original | E50: Economia sin Sector Publico: Ahorro voluntario | Neutralidad del Sector Publico: Sistema de Capitalizacion | Intervencion del Sector Publico: Sistema de Reparto | F50: 4 | G50: Completo
A51: Modelo AK | B51: 3.A.44 | C51: Teorías del crecimiento económico (II) | D51: Versión original | E51: Supuestos | Desarrollo analitico | Funcion de SOBELOW | F51: 3 | G51: Parcial
B52: 3.A.44 | C52: Teorías del crecimiento económico (II) | D52: Externalidades / learning-by-doing (Arrow 1962; Romer 1986) | E52: Externalidades de Capital ( K ) | F52: 1 | G52: Parcial
B53: 3.A.38 | C53: Política Fiscal | D53: Gasto público productivo (Barro 1990) | E53: Desarrollo analitico | F53: 2 | G53: Parcial
A54: Modelo ricardiano | B54: 3.A.2 | C54: Los economistas clásicos y MARX | D54: Versión original | E54: Teoria de la Ventaja Comparativa | F54: 1 | G54: Parcial
B55: 3.B.5 | C55: Teoría del Comercio Internacional (I) | D55: Versión original | E55: Coste de oportunidad: Relaciones de transformacion | Ventaja comparativa | Implicaciones de Politica Economica: Aumento de la produccion | Autarquia: Desarrollo del modelo | Precios relativos: Produccion | Apertura comercial | Oferta y Demanda relativas: Determinacion del precio relativo | F55: 9 | G55: Completo
A56: Empresas heterogéneas | B56: 3.B.6 | C56: Teoría del Comercio Internacional (II) | D56: Versión original | E56: Demanda: CES-isoelastica | Implicaciones de Politica Economica: Apertura al comercio | Modelo de MELITZ: Desarrollos auxiliares | F56: 10 | G56: Completo
B57: 3.B.7 | C57: La Política Comercial (I) | D57: Marco ACR / "modelo ARA" (Arkolakis-Costinot-Rodríguez-Clare 2012) | E57: Modelo ARA: Equilibrio General | F57: 35 | G57: Completo
B58: 3.B.6 | C58: Teoría del Comercio Internacional (II) | D58: Melitz-Ottaviano (2008) | E58: Demanda: CES-isoelastica | Condicion de libre entrada | F58: 2 | G58: Parcial
B59: 3.B.7 | C59: La Política Comercial (I) | D59: Melitz-Ottaviano (2008) | E59: Productor | Condicion de libre entrada: Beneficio esperado | Modelo MELITZ-OTTAVIANO: Comercio intrasectorial y aranceles | F59: 43 | G59: Completo
B60: 3.B.10 | C60: Teoría de la integración económica | D60: Melitz-Ottaviano (2008) | E60: Marco de Equilibrio Parcial: efectos sobre la estructura del mercado | F60: 1 | G60: Parcial
A61: Mundell-Fleming | B61: 3.A.38 | C61: Política Fiscal | D61: Versión original | E61: Economia abierta: Modelo MUNDELL-FLEMING | F61: 1 | G61: Parcial
B62: 3.B.12 | C62: Balanza de Pagos (II) | D62: IS-LM-BP | E62: Modelo MUNDELL-FLEMING: Equilibrio General | F62: 1 | G62: Parcial
A63: Equilibrio de cartera | B63: 3.B.12 | C63: Balanza de Pagos (II) | D63: Versión original | E63: Mercado de Activos: Cuenta Financiera | Mercado de Bienes: Cuenta Corriente | F63: 2 | G63: Parcial
B64: 3.B.12 | C64: Balanza de Pagos (II) | D64: McKinnon (1969) | E64: Mercado de Activos: Cuenta Financiera | F64: 1 | G64: Parcial
B65: 3.B.14 | C65: Teorías de la determinación del Tipo de Cambio | D65: McKinnon (1969) | E65: Mercado de Activos: Cuenta Financiera | Mercado de Bienes: Cuenta Corriente | F65: 2 | G65: Parcial
A66: Nueva macroeconomía de economía abierta (NOEM) | B66: 3.A.32 | C66: El modelo de oferta y demanda agregada | D66: Versión original | E66: Politica Fiscal: FURLANETTO (2006) | F66: 1 | G66: Parcial
B67: 3.A.32 | C67: El modelo de oferta y demanda agregada | D67: Pequeña economía abierta NK (Galí-Monacelli 2005) | E67: Economia pequena y abierta: GALI y MONACELLI (2005) | Curva IS: Optimizacion de los Hogares | Derivacion del modelo GALI y MONACELLI (2005) -- NOEM | F67: 8 | G67: Completo
B68: 3.A.42 | C68: Teorías de los ciclos económicos | D68: Pequeña economía abierta NK (Galí-Monacelli 2005) | E68: Modelo canonico: Derivacion analitica | ¿Divina Coincidencia? Politica Monetaria y Shocks | F68: 2 | G68: Parcial
A69: CAPM | B69: 3.B.2 | C69: La empresa y las decisiones de inversión | D69: Versión original | E69: Riesgo no diversificable: Obtencion | F69: 1 | G69: Parcial
B70: 3.B.4 | C70: Análisis del crecimiento de la empresa | D70: Versión original | E70: Diversificacion del riesgo | F70: 1 | G70: Parcial
B71: 3.B.23 | C71: Análisis de los instrumentos financieros de renta variable | D71: Versión original | E71: Nueva medida de riesgo: la beta ( ) | Demostracion | Linea del mercado de activos (SML) | Gestion activa de carteras: busqueda de alpha y analisis fundamental | F71: 15 | G71: Completo
A72: Enfoque intertemporal de la cuenta corriente | B72: 3.B.15 | C72: Análisis comparado de los distintos regímenes cambiarios | D72: Versión original | E72: Efectos: Modelo intertemporal de consumo con restricciones de capital | F72: 1 | G72: Parcial
B73: 3.B.29 | C73: Financiación exterior del desarrollo económico | D73: Versión original | E73: Planteamiento del modelo con horizonte infinito | Analisis: | F73: 6 | G73: Completo
B74: 3.B.12 | C74: Balanza de Pagos (II) | D74: Modelo de dos períodos (Obstfeld-Rogoff 1996) | E74: Modelo de OBSTFELD-ROGOFF: Dos periodos | Desarrollo grafico | F74: 2 | G74: Parcial
A75: Curva de Phillips | B75: 3.A.5 | C75: La síntesis neoclásica | D75: Versión original | E75: La curva de PHILLIPS | F75: 3 | G75: Parcial
B76: 3.A.6 | C76: La nueva macroeconomía clásica | D76: Versión original | E76: Curva de PHILLIPS y sorpresa monetaria | F76: 1 | G76: Parcial
B77: 3.A.28 | C77: La tasa natural de paro y de la NAIRU | D77: Versión original | E77: Descomposicion del desempleo: Desempleo y Tasa Natural | Desarrollo teorico de la Curva de PHILLIPS: LIPSEY (SNC) | F77: 5 | G77: Completo
B78: 3.A.32 | C78: El modelo de oferta y demanda agregada | D78: Versión original | E78: Shocks (negativos): Costes de produccion | F78: 1 | G78: Parcial
B79: 3.A.5 | C79: La síntesis neoclásica | D79: Aumentada con expectativas / tasa natural (Friedman 1968, Phelps 1967) | E79: Expectativas adaptativas | F79: 2 | G79: Parcial
B80: 3.A.28 | C80: La tasa natural de paro y de la NAIRU | D80: Aumentada con expectativas / tasa natural (Friedman 1968, Phelps 1967) | E80: Tasa natural de paro: FRIEDMAN | F80: 1 | G80: Parcial
B81: 3.A.7 | C81: La nueva economía Keynesiana | D81: Curva de Phillips neokeynesiana / híbrida | E81: Curva de PHILLIPS de la NEK | Modificaciones: Curvas de PHILLIPS hibridas | F81: 2 | G81: Parcial
B82: 3.A.32 | C82: El modelo de oferta y demanda agregada | D82: Curva de Phillips neokeynesiana / híbrida | E82: Curva de PHILLIPS: Optimizacion de las empresas | F82: 1 | G82: Parcial
B83: 3.A.42 | C83: Teorías de los ciclos económicos | D83: Curva de Phillips neokeynesiana / híbrida | E83: Curva de PHILLIPS: Empresas | F83: 1 | G83: Parcial
A84: Teoría cuantitativa del dinero | B84: 3.A.5 | C84: La síntesis neoclásica | D84: Versión original | E84: La Demanda de dinero | Mecanismos de Transmision: la Teoria Cuantitativa del Dinero | F84: 5 | G84: Completo
B85: 3.A.35 | C85: Teorías de la demanda de dinero | D85: Versión original | E85: Enfoque Neoclasico: la Teoria Cuantitativa del Dinero | F85: 1 | G85: Parcial
B86: 3.A.41 | C86: La inflación | D86: Versión original | E86: Limitaciones: Enfoque Monetario | F86: 1 | G86: Parcial
B87: 3.A.35 | C87: Teorías de la demanda de dinero | D87: Neocuantitativismo (Friedman 1956) | E87: Enfoque Monetarista: Neocuantitativismo | F87: 2 | G87: Parcial
B88: 3.A.38 | C88: Política Fiscal | D88: Neocuantitativismo (Friedman 1956) | E88: Enfoque Monetarista | F88: 1 | G88: Parcial
B89: 3.A.3 | C89: Los economistas neoclásicos | D89: Saldos reales de Cambridge (M = kPY) | E89: Teoria del dinero | F89: 1 | G89: Parcial
A90: Equivalencia ricardiana | B90: 3.A.38 | C90: Política Fiscal | D90: Versión original | E90: Financiacion del gasto: Equivalencia Ricardiana | F90: 1 | G90: Parcial
B91: 3.A.39 | C91: Déficit Público | D91: Versión original | E91: ¿Cual es la mejor forma de financiar el Gasto del Estado?: Equivalencia Ricardiana | F91: 1 | G91: Parcial
B92: 3.A.40 | C92: Efectividad e interrelación de las Políticas Monetarias y Fiscales | D92: Versión original | E92: Equivalencia Ricardiana: Politica Fiscal expansiva (ejemplo) | F92: 1 | G92: Parcial
A93: Dinámica y sostenibilidad de la deuda pública | B93: 3.A.39 | C93: Déficit Público | D93: Versión original | E93: Deficit Publico: Marco General | Deficit Publico: Conceptos | Inflacion | Ciclo Economico | Aportaciones de KEYNES | Monetarismo | Politica Fiscal y Politica Monetaria: Vinculo | Dinamica del Deficit Publico | Sostenibilidad de la Deuda Publica | Deuda Publica: Economia Cerrada | Deficit Publico: Economia Abierta | F93: 18 | G93: Completo
B94: 3.B.29 | C94: Financiación exterior del desarrollo económico | D94: Deuda externa: brecha de absorción | E94: Ajustes: ¿Como podemos evitar una crisis de deuda? | F94: 1 | G94: Parcial
A95: Monopolio | B95: 3.A.17 | C95: Análisis de mercados (II) | D95: Versión original | E95: Desarrollo formal | Condiciones necesarias: CPO | Indice de Lerner | Mercado de factores: Ineficiecia asignativa | Demandas dependientes y costes separables | F95: 6 | G95: Completo
B96: 3.A.20 | C96: Regulación y Poder de mercado | D96: Versión original | E96: Poder de mercado | F96: 2 | G96: Parcial
B97: 3.A.17 | C97: Análisis de mercados (II) | D97: Discriminación de precios | E97: Discriminacion de primer grado: Informacion perfecta | F97: 1 | G97: Parcial
B98: 3.A.17 | C98: Análisis de mercados (II) | D98: Monopsonio | E98: Monopsonio | F98: 1 | G98: Parcial
A99: Incidencia impositiva en equilibrio parcial | B99: 3.A.16 | C99: Análisis de mercados (I) | D99: Versión original | E99: Impuesto sobre el consumo | F99: 3 | G99: Parcial
B100: 4.B.8 | C100: Teoría impositiva (II): Traslación e incidencia de los impuestos en mercados competitivos y monopolistas | D100: Versión original | E100: ¿Como depende la traslacion del precio? La determinacion del precio | F100: 1 | G100: Parcial
...

Sheet Desarrollos
A1: Área | B1: Familia (modelo original) | C1: Referencia original | D1: Forma desarrollada | E1: Tipo | F1: Tema | G1: Título del tema | H1: Epígrafe(s) donde se desarrolla | I1: Nº bloques de ecuaciones | J1: Grado | K1: Muestra de la formalización (LaTeX)
A2: Microeconomía | B2: Descuento cuasi-hiperbólico | C2: Laibson (1997) | D2: Versión original | E2: Original | F2: 3.A.29 | G2: Modelización dinámica de las tomas de decisiones | H2: Preferencias Intertemporales: Funcion de Utilidad Intertemporal | I2: 1 | J2: =IF(I2>=4,"Completo","Parcial") -> Parcial | K2: D(t)=\frac{1}{1+k\cdot t}
A3: Microeconomía | B3: Asignación del tiempo | C3: Becker (1965) | D3: Versión original | E3: Original | F3: 3.A.25 | G3: La teoría neoclásica del mercado de trabajo | H3: Modelo de BECKER | Duracion optima de la formacion | I3: 2 | J3: =IF(I3>=4,"Completo","Parcial") -> Parcial | K3: &h(t)=\theta\;\sigma(t)\;h(t)\qquad \text{Donde,}\quad \begin{cases} \text{ $h(t)\equiv$ \; Designa el stock de capital humano, en $t$} \text{ $\theta\equiv \;$ Parámetro de eficiencia del individuo} \text{ $\sigma(t)\eq
A4: Microeconomía | B4: Elección ocio-consumo (oferta de trabajo neoclásica) | C4: Robbins (1930) / tradición neoclásica | D4: Versión original | E4: Original | F4: 3.A.6 | G4: La nueva macroeconomía clásica | H4: Modelo: Optimizacion intertemporal Ocio-Consumo | I4: 1 | J4: =IF(I4>=4,"Completo","Parcial") -> Parcial | K4: &\boxed{ &\max_{\{c_1, c_2, L_1, L_2\}}{U}=u(c_1, 1- L_1)+\beta(c_2, 1-L_2) &\text{s.a.}\quad c_1+\frac{1}{1+r}c_2=w_1L_1+\frac{1}{1+r}w_2L_2 }\to\text{Resolvemos por}\; \mathcal{L}\;\text{y obtenemos CPO's} &\boxed{\fra
A5: Microeconomía | B5: Elección ocio-consumo (oferta de trabajo neoclásica) | C5: Robbins (1930) / tradición neoclásica | D5: Versión original | E5: Original | F5: 3.A.25 | G5: La teoría neoclásica del mercado de trabajo | H5: El problema del consumidor: Eleccion entre consumo y ocio | Variaciones en la Funcion de Oferta Marshalliana | I5: 4 | J5: =IF(I5>=4,"Completo","Parcial") -> Completo | K5: &\text{\textbf{Definición:} Función de oferta de trabajo Marshalliana o no compensada} &\hspace{10em}\boxed{ L^*=\Gamma(w,R_0)}
A6: Microeconomía | B6: Elección ocio-consumo (oferta de trabajo neoclásica) | C6: Robbins (1930) / tradición neoclásica | D6: Oferta intertemporal de trabajo (Lucas-Rapping 1969) | E6: Variante | F6: 3.A.25 | G6: La teoría neoclásica del mercado de trabajo | H6: Obtencion de la oferta intertemporal de trabajo | I6: 4 | J6: =IF(I6>=4,"Completo","Parcial") -> Completo | K6: &\max_{\{C_t, L_t\}}{\sum_{t=0}^TU(C_t,L_t,t)} \qquad \text{s.a.}\quad (1+r_t)A_{t-1}+B_t+w_t(1-L_t)-C_t\leq A_t\quad \forall t \text{Donde,} \quad &\begin{cases} A_t\equiv \;\text{Activos del agente} B_t\equiv \;\text{R
A7: Microeconomía | B7: Competencia monopolística | C7: Chamberlin (1933) | D7: Dixit-Stiglitz (1977) | E7: Variante | F7: 3.A.18 | G7: Análisis de mercados (III) | H7: Consumidor: Preferencia por la variedad | Condicion CES: Simplificacion | Elasticidades-renta unitarias | Elasticidad-precio de la demanda de una variedad | Elasticidad de sustitucion: Intersectorial e Intrasectorial | Indice de precios: Deflactor del bienestar | Productor: Competencia monopolistica | Condicion de libre entrada | I7: 9 | J7: =IF(I7>=4,"Completo","Parcial") -> Completo | K7: &\boxed{ &\max U=U\left(m,\;\left\{\sum_{i=1}^Ix_i^\rho\right\}^{\frac{1}{\rho}}\right) &\text{s.a.}\quad m+\sum_{i=1}^Ip_i\cdot x_i\leq m_0 } &\text{(Solución: 2 Etapas)} &\Longrightarrow \left\{ &\underset{\text{ $S(\c
A8: Microeconomía | B8: Competencia monopolística | C8: Chamberlin (1933) | D8: Dixit-Stiglitz (1977) | E8: Variante | F8: 3.B.6 | G8: Teoría del Comercio Internacional (II) | H8: Demanda: CES-isoelastica | Productor: Simetria en costes | I8: 3 | J8: =IF(I8>=4,"Completo","Parcial") -> Parcial | K8: &\boxed{ &\max U=U\left(m,\underbrace{\;\left\{\sum_{i=1}^Ix_i^\rho\right\}^{\frac{1}{\rho}}}_{V(\cdot)}\right) &\text{s.a.}\quad m+\sum_{i=1}^Ip_i\cdot x_i\leq m_0 }\qquad \substack{\text{Problema dual}\\\text{del consu
A9: Microeconomía | B9: Duopolio de Cournot | C9: Cournot (1838) | D9: Versión original | E9: Original | F9: 3.A.19 | G9: Análisis de mercados (IV) | H9: Desarrollo | I9: 2 | J9: =IF(I9>=4,"Completo","Parcial") -> Parcial | K9: &\boxed{ &\max_{x_i}\Pi_i(x_i)=x_i\cdot P^d_x(x_i+x_{-i})-C_i(x_i) &\text{s.a.}\qquad \Pi_i(x_i)\ge 0 }\qquad \text{si,}\; \left\{ &\Pi_i(x_i)\in\mathcal C^2\quad \text{y,}\quad \frac{\partial^2 \Pi_i(x_i)}{\partial^2 x_
A10: Microeconomía | B10: Duopolio de Cournot | C10: Cournot (1838) | D10: Variaciones conjeturales (Bowley 1924) | E10: Variante | F10: 3.A.19 | G10: Análisis de mercados (IV) | H10: Variacion conjentural: ¿Que es? Derivacion analitica | I10: 8 | J10: =IF(I10>=4,"Completo","Parcial") -> Completo | K10: &\text{Empresa 1}:&&F_1(x_1,x_2,\gamma_1)\equiv \frac{\partial r_1}{\partial x_1}+\gamma_1\frac{\partial r_1}{\partial x_2}-c_1'(x_1)=0 &&&\underset{\substack{\text{ podemos resolver}\\\text{ para $x_1$ como función de $
A11: Microeconomía | B11: Duopolio de Bertrand | C11: Bertrand (1883) | D11: Versión original | E11: Original | F11: 3.A.19 | G11: Análisis de mercados (IV) | H11: Desarrollo formal | I11: 1 | J11: =IF(I11>=4,"Completo","Parcial") -> Parcial | K11: &\boxed{ &\max_{p_i}\Pi_i(p_,p_{-i})=p_iD_i(p_i,p_{-i})-C_i(D_i(p_i,p_{-i})) &\text{s.a.}\qquad \Pi_i(x_i)\ge 0 }\qquad \text{si,}\; \left\{ &\Pi_i(x_i)\in\mathcal C^2\quad \text{y,}\quad \frac{\partial^2 \Pi_i(x_i)}{\pa
A12: Microeconomía | B12: Ciudad lineal (diferenciación espacial) | C12: Hotelling (1929) | D12: Versión original | E12: Original | F12: 3.A.18 | G12: Análisis de mercados (III) | H12: Costes de transporte: lineales | Costes de transporte: Cuadraticos | Modelos espaciales: Resolucion analitica | I12: 3 | J12: =IF(I12>=4,"Completo","Parcial") -> Parcial | K12: &p_i+t\cdot\tilde x=p+t\left(\frac{1}{n}-\tilde x\right)\Longrightarrow t\left(2\tilde x-\frac{1}{n}\right)=p-p_i\Longrightarrow \tilde x=\frac{1}{2n}+\frac{p-p_i}{2t} &\overset{\substack{\text{ Como $i$ tiene el}\\\text
A13: Microeconomía | B13: Ciudad lineal (diferenciación espacial) | C13: Hotelling (1929) | D13: Ciudad circular (Salop 1979) | E13: Variante | F13: 3.A.18 | G13: Análisis de mercados (III) | H13: Implicaciones de Politica Economica | I13: 1 | J13: =IF(I13>=4,"Completo","Parcial") -> Parcial | K13: T=n\cdot 2\cdot \int_{0}^{(1/2)\cdot n}t\cdot x\cdot \mathrm dx=n\cdot t\left(\frac{1}{2n}\right)^{2}=\frac{t}{4n}
... A181: Finanzas | B181: Pérdida esperada e inesperada (IRB / Vasicek ASRF) | C181: Vasicek (2002) / Basilea II | D181: Versión original | E181: Original | F181: 3.B.27 | G181: Regulación financiera y no-bancaria | H181: Riesgo de credito: Perdida esperadas/inesperadas | I181: 1 | J181: =IF(I181>=4,"Completo","Parcial") -> Parcial | K181: &\text{Pérdida esperada}:&&{\textbf{EL}}=\overset{{ \substack{\text{Probabilidad}\\\text{Incumplimiento}}}}{\text{PD}}\cdot \underset{{ \substack{\text{Pérdida dado}\\\text{Impago}}}}{\text{LGD}}\cdot\overset{{ \substack

Sheet Matriz
A1: Familia (modelo original) | B1: Nº temas | C1: 3.A.2 | D1: 3.A.3 | E1: 3.A.4 | F1: 3.A.5 | G1: 3.A.6 | H1: 3.A.7 | I1: 3.A.12 | J1: 3.A.13 | K1: 3.A.16 | L1: 3.A.17 | M1: 3.A.18 | N1: 3.A.19 | O1: 3.A.20 | P1: 3.A.21 | Q1: 3.A.22 | R1: 3.A.23 | S1: 3.A.25 | T1: 3.A.26 | U1: 3.A.27 | V1: 3.A.28 | W1: 3.A.29 | X1: 3.A.31 | Y1: 3.A.32 | Z1: 3.A.33 | AA1: 3.A.34 | AB1: 3.A.35 | AC1: 3.A.37 | AD1: 3.A.38 | AE1: 3.A.39 | AF1: 3.A.40 | AG1: 3.A.41 | AH1: 3.A.42 | AI1: 3.A.43 | AJ1: 3.A.44 | AK1: 3.B.2 | AL1: 3.B.3 | AM1: 3.B.4 | AN1: 3.B.5 | AO1: 3.B.6 | AP1: 3.B.7 | AQ1: 3.B.10 | AR1: 3.B.12 | AS1: 3.B.14 | AT1: 3.B.15 | AU1: 3.B.17 | AV1: 3.B.19 | AW1: 3.B.23 | AX1: 3.B.24 | AY1: 3.B.25 | AZ1: 3.B.26 | BA1: 3.B.27 | BB1: 3.B.29 | BC1: 3.B.31 | BD1: 4.B.8 | BE1: 4.B.10 | BF1: 4.B.11
A2: Descuento cuasi-hiperbólico | B2: =COUNTA(C2:BF2) -> 1 | W2: O
A3: Asignación del tiempo | B3: =COUNTA(C3:BF3) -> 1 | S3: O
A4: Elección ocio-consumo (oferta de trabajo neoclásica) | B4: =COUNTA(C4:BF4) -> 2 | G4: O | S4: O+V
A5: Competencia monopolística | B5: =COUNTA(C5:BF5) -> 2 | M5: V | AO5: V
A6: Duopolio de Cournot | B6: =COUNTA(C6:BF6) -> 1 | N6: O+V
A7: Duopolio de Bertrand | B7: =COUNTA(C7:BF7) -> 1 | N7: O
A8: Ciudad lineal (diferenciación espacial) | B8: =COUNTA(C8:BF8) -> 1 | M8: O+V
A9: Principal-agente | B9: =COUNTA(C9:BF9) -> 1 | J9: O+V
A10: Filtrado en mercado de seguros | B10: =COUNTA(C10:BF10) -> 1 | J10: V
A11: Señalización en el mercado de trabajo | B11: =COUNTA(C11:BF11) -> 2 | J11: O | AL11: V
A12: Equilibrio general walrasiano / Arrow-Debreu | B12: =COUNTA(C12:BF12) -> 2 | K12: O | P12: O+V
A13: Tablas input-output | B13: =COUNTA(C13:BF13) -> 1 | X13: O
A14: Análisis envolvente de datos (DEA) | B14: =COUNTA(C14:BF14) -> 1 | I14: O
A15: Frontera estocástica (SFA) | B15: =COUNTA(C15:BF15) -> 1 | I15: O
A16: Regulación con información asimétrica | B16: =COUNTA(C16:BF16) -> 1 | O16: O
A17: Imposición / tarificación óptima de Ramsey | B17: =COUNTA(C17:BF17) -> 2 | O17: V | BF17: O
A18: Imposición óptima sobre la renta | B18: =COUNTA(C18:BF18) -> 2 | BE18: V | BF18: O
A19: Bienes públicos: provisión eficiente | B19: =COUNTA(C19:BF19) -> 1 | R19: O+V
A20: Modelo keynesiano simple (renta-gasto / aspa keynesiana) | B20: =COUNTA(C20:BF20) -> 4 | E20: V | AD20: O | AF20: O | AS20: O
A21: IS-LM | B21: =COUNTA(C21:BF21) -> 4 | F21: O | AD21: O | AE21: V | AF21: O
A22: Ciclo Real (RBC) | B22: =COUNTA(C22:BF22) -> 1 | AH22: O
A23: Inconsistencia temporal de la política | B23: =COUNTA(C23:BF23) -> 2 | G23: O | R23: O
A24: Islas de Lucas (información imperfecta) | B24: =COUNTA(C24:BF24) -> 2 | G24: O | AH24: O
A25: Costes de menú | B25: =COUNTA(C25:BF25) -> 1 | H25: O+V
A26: Nuevo keynesiano de tres ecuaciones (NEK-2) | B26: =COUNTA(C26:BF26) -> 5 | H26: O | V26: O | AC26: O | AG26: O | AH26: O
A27: Renta permanente | B27: =COUNTA(C27:BF27) -> 3 | F27: O | W27: O | Z27: O+V
A28: Ciclo vital | B28: =COUNTA(C28:BF28) -> 1 | Z28: O
A29: q de Tobin | B29: =COUNTA(C29:BF29) -> 1 | AA29: O+V
A30: Opciones reales de inversión | B30: =COUNTA(C30:BF30) -> 2 | AA30: O | AK30: O
A31: Acelerador financiero | B31: =COUNTA(C31:BF31) -> 1 | AH31: O
A32: Demanda de dinero por inventario | B32: =COUNTA(C32:BF32) -> 1 | AB32: O+V
A33: Dinero en la función de utilidad (MIU) | B33: =COUNTA(C33:BF33) -> 1 | AB33: O
A34: Cash-in-advance (CIA) | B34: =COUNTA(C34:BF34) -> 1 | AB34: O
A35: Hiperinflación | B35: =COUNTA(C35:BF35) -> 1 | AG35: O
A36: Suavización impositiva | B36: =COUNTA(C36:BF36) -> 1 | AD36: O
A37: Salarios de eficiencia | B37: =COUNTA(C37:BF37) -> 2 | H37: O | U37: O+V
A38: Monopolio sindical | B38: =COUNTA(C38:BF38) -> 1 | U38: V
A39: Búsqueda y emparejamiento (DMP) | B39: =COUNTA(C39:BF39) -> 2 | T39: O | V39: O
A40: NAIRU / WS-PS | B40: =COUNTA(C40:BF40) -> 2 | V40: O | AG40: O
A41: Harrod-Domar | B41: =COUNTA(C41:BF41) -> 1 | E41: O
A42: Solow-Swan | B42: =COUNTA(C42:BF42) -> 1 | AI42: O
A43: Ramsey-Cass-Koopmans | B43: =COUNTA(C43:BF43) -> 2 | W43: O | AI43: O
A44: Generaciones solapadas | B44: =COUNTA(C44:BF44) -> 3 | W44: O | AB44: O | AD44: O
A45: Modelo AK | B45: =COUNTA(C45:BF45) -> 2 | AD45: V | AJ45: O+V
A46: Capital humano | B46: =COUNTA(C46:BF46) -> 1 | AJ46: O
A47: Expansión de variedades (I+D) | B47: =COUNTA(C47:BF47) -> 1 | AJ47: O
A48: Modelo ricardiano | B48: =COUNTA(C48:BF48) -> 2 | C48: O | AN48: O
A49: Factores específicos | B49: =COUNTA(C49:BF49) -> 1 | AN49: O
A50: Heckscher-Ohlin | B50: =COUNTA(C50:BF50) -> 1 | AN50: O
A51: Nueva teoría del comercio (rendimientos crecientes) | B51: =COUNTA(C51:BF51) -> 1 | AO51: O
A52: Empresas heterogéneas | B52: =COUNTA(C52:BF52) -> 3 | AO52: O+V | AP52: V | AQ52: V
A53: Modelo de gravedad | B53: =COUNTA(C53:BF53) -> 1 | AQ53: O
A54: Enfoque de elasticidades | B54: =COUNTA(C54:BF54) -> 1 | AR54: O
A55: Enfoque monetario de la balanza de pagos | B55: =COUNTA(C55:BF55) -> 1 | AR55: O
A56: Mundell-Fleming | B56: =COUNTA(C56:BF56) -> 2 | AD56: O | AR56: V
A57: Modelo monetario del tipo de cambio (precios flexibles) | B57: =COUNTA(C57:BF57) -> 1 | AS57: O+V
A58: Equilibrio de cartera | B58: =COUNTA(C58:BF58) -> 2 | AR58: O+V | AS58: V
A59: Nueva macroeconomía de economía abierta (NOEM) | B59: =COUNTA(C59:BF59) -> 2 | Y59: O+V | AH59: V
A60: Crisis cambiarias de primera generación | B60: =COUNTA(C60:BF60) -> 1 | AU60: O
A61: Crisis cambiarias de segunda generación | B61: =COUNTA(C61:BF61) -> 1 | AU61: V
A62: Crisis cambiarias de tercera generación | B62: =COUNTA(C62:BF62) -> 1 | AU62: O
A63: Selección de carteras media-varianza | B63: =COUNTA(C63:BF63) -> 1 | AW63: O+V
A64: CAPM | B64: =COUNTA(C64:BF64) -> 3 | AK64: O | AM64: O | AW64: O
A65: APT (arbitraje) | B65: =COUNTA(C65:BF65) -> 1 | AW65: O
A66: Valoración de opciones | B66: =COUNTA(C66:BF66) -> 1 | AY66: O
A67: Riesgo de crédito estructural | B67: =COUNTA(C67:BF67) -> 1 | AZ67: O+V
A68: Descuento de dividendos / crecimiento constante | B68: =COUNTA(C68:BF68) -> 1 | AK68: O
A69: Irrelevancia de la estructura financiera | B69: =COUNTA(C69:BF69) -> 1 | AL69: O
A70: Pánicos bancarios | B70: =COUNTA(C70:BF70) -> 1 | AZ70: O
A71: Racionamiento del crédito | B71: =COUNTA(C71:BF71) -> 1 | H71: O
A72: DICE | B72: =COUNTA(C72:BF72) -> 1 | BC72: O
A73: Costes de ajuste (demanda dinámica de factores) | B73: =COUNTA(C73:BF73) -> 1 | T73: O
A74: Enfoque intertemporal de la cuenta corriente | B74: =COUNTA(C74:BF74) -> 3 | AR74: V | AT74: O | BB74: O
A75: Teoría del valor-trabajo y reproducción | B75: =COUNTA(C75:BF75) -> 1 | C75: O
A76: Modelo macroeconómico clásico/neoclásico | B76: =COUNTA(C76:BF76) -> 1 | E76: O
A77: Curva de Phillips | B77: =COUNTA(C77:BF77) -> 6 | F77: O+V | G77: O | H77: V | V77: O+V | Y77: O+V | AH77: V
A78: Teoría cuantitativa del dinero | B78: =COUNTA(C78:BF78) -> 5 | D78: V | F78: O | AB78: O+V | AD78: V | AG78: O
A79: Preferencia por la liquidez | B79: =COUNTA(C79:BF79) -> 1 | AB79: O
A80: Equivalencia ricardiana | B80: =COUNTA(C80:BF80) -> 3 | AD80: O | AE80: O | AF80: O
A81: Dinámica y sostenibilidad de la deuda pública | B81: =COUNTA(C81:BF81) -> 2 | AE81: O | BB81: V
A82: Teoría fiscal del nivel de precios | B82: =COUNTA(C82:BF82) -> 1 | AG82: O
A83: Inflación por conflicto distributivo | B83: =COUNTA(C83:BF83) -> 1 | AG83: O
A84: Competencia perfecta (equilibrio parcial) | B84: =COUNTA(C84:BF84) -> 1 | K84: O
A85: Monopolio | B85: =COUNTA(C85:BF85) -> 2 | L85: O+V | O85: O
A86: Segundo óptimo | B86: =COUNTA(C86:BF86) -> 1 | Q86: O
A87: Externalidades y corrección pigouviana | B87: =COUNTA(C87:BF87) -> 1 | R87: O+V
A88: Incidencia impositiva en equilibrio parcial | B88: =COUNTA(C88:BF88) -> 2 | K88: O | BD88: O
A89: Demanda de trabajo neoclásica | B89: =COUNTA(C89:BF89) -> 1 | S89: O
A90: Capital humano y ecuación de ingresos | B90: =COUNTA(C90:BF90) -> 1 | S90: O
A91: Paridad de poder adquisitivo | B91: =COUNTA(C91:BF91) -> 1 | AS91: O
A92: Paridad de intereses | B92: =COUNTA(C92:BF92) -> 1 | AS92: O+V
A93: Burbujas racionales | B93: =COUNTA(C93:BF93) -> 2 | AH93: O | AS93: O
A94: Coordinación internacional (juego de cooperación) | B94: =COUNTA(C94:BF94) -> 1 | AV94: O
A95: Arancel en equilibrio parcial / arancel óptimo | B95: =COUNTA(C95:BF95) -> 1 | AP95: O
A96: Estructura temporal: expectativas y hábitat | B96: =COUNTA(C96:BF96) -> 1 | AX96: O+V
A97: Pérdida esperada e inesperada (IRB / Vasicek ASRF) | B97: =COUNTA(C97:BF97) -> 2 | AZ97: O | BA97: O
A98: Nº familias desarrolladas en el tema | C98: =COUNTA(C2:C97) -> 2 | D98: =COUNTA(D2:D97) -> 1 | E98: =COUNTA(E2:E97) -> 3 | F98: =COUNTA(F2:F97) -> 4 | G98: =COUNTA(G2:G97) -> 4 | H98: =COUNTA(H2:H97) -> 5 | I98: =COUNTA(I2:I97) -> 2 | J98: =COUNTA(J2:J97) -> 3 | ... BF98: =COUNTA(BF2:BF97) -> 2
A100: O = se desarrolla la versión original · V = solo una variante · O+V = ambas

Sheet Formalización sin modelo
A1: Tema | B1: Título del tema | C1: Ruta de epígrafes | D1: Nº bloques
A2: 3.A.3 | B2: Los economistas neoclásicos | C2: Aportaciones de IRVING FISHER al marco Neoclasico | D2: 1
A3: 3.A.4 | B3: El pensamiento económico de KEYNES | C3: La economia post-keynesiana > Escuela de Cambridge > La controversia del capital | D3: 1
A4: 3.A.6 | B4: La nueva macroeconomía clásica | C4: Contexto historico > Revolucion metodologica: Supuestos fundamentales y Caracteristicas > Conducta de los Agentes Economicos: Hipotesis de las Expectativas Racionales | D4: 2
A5: 3.A.7 | B5: La nueva economía Keynesiana | C5: Primera generacion > Rigideces reales > Mercado de bienes | D5: 1
A6: 3.A.9 | B6: Teoría de la demanda del consumidor (II) | C6: Analisis Dual: Aplicaciones > Ecuacion de SLUTSKY > Derivacion formal | D6: 5
A7: 3.A.9 | B7: Teoría de la demanda del consumidor (II) | C7: Primal vs. Dual > Problema Dual: Minimizacion del gasto > Desarrollo | D7: 1
A8: 3.A.9 | B8: Teoría de la demanda del consumidor (II) | C8: Primal vs. Dual > Problema Dual: Minimizacion del gasto > Especificacion | D8: 1
A9: 3.A.9 | B9: Teoría de la demanda del consumidor (II) | C9: Primal vs. Dual > Problema Dual: Minimizacion del gasto > Funcion Valor: Funcion de Gasto | D9: 2
A10: 3.A.9 | B10: Teoría de la demanda del consumidor (II) | C10: Primal vs. Dual > Problema Dual: Minimizacion del gasto > Solucion: SCEDC | D10: 2
A11: 3.A.9 | B11: Teoría de la demanda del consumidor (II) | C11: Primal vs. Dual > Problema Primal. Maximizacion de la Utilidad > Especificacion | D11: 1
A12: 3.A.9 | B12: Teoría de la demanda del consumidor (II) | C12: Primal vs. Dual > Relaciones de Dualidad > Dualidad entre Funciones de Valor | D12: 1
A13: 3.A.9 | B13: Teoría de la demanda del consumidor (II) | C13: Primal vs. Dual > Relaciones de Dualidad > Teorema Basico de la Dualidad: Dualidad entre soluciones | D13: 1
... A216: 4.B.16 | B216: Sistema Fiscal en España (I): Impuesto sobre la Renta de las Personas Físicas | C216: Divergencias estructurales: ¿Como se define la renta gravable en Espana? | D216: 1

Sheet Notas
A1: Criterio | B1: Un modelo cuenta como DESARROLLADO en un tema solo si hay al menos un bloque de ecuaciones (\eqblock, \[ \], equation o $$) que formaliza alguno de sus postulados. Las menciones en texto, aunque sean muchas, no cuentan.
A2: Atribución | B2: Cada bloque se asigna al modelo nombrado en (1) su pie de ecuación (2º argumento de \eqblock), (2) el epígrafe más cercano o sus epígrafes superiores, (3) una atribución manual por ruta de epígrafes cuando el texto no nombra el modelo, o (4) en último caso, la mención más próxima en los 1.200 caracteres previos. Todas las atribuciones por (3) y (4) se revisaron leyendo la ecuación.
A3: Revisión manual | B3: Se descartaron 30 atribuciones erróneas y se reasignaron 14 (p. ej. el bloque de "Optimización modelo RAMSEY (ocio-consumo)" en 3.A.35 es shopping-time, no RCK; la "minimización de pérdida social de BARRO" en 3.A.38 es suavización impositiva, no inconsistencia temporal; el modelo de dos períodos de Obstfeld-Rogoff en 3.B.12 es el enfoque intertemporal de la cuenta corriente, no la NOEM-Redux).
A4: Grado | B4: Completo = 4 o más bloques de ecuaciones atribuidos al modelo en el tema; Parcial = 1 a 3. Es un umbral cuantitativo, no un juicio de calidad: un único bloque largo puede contener el modelo entero. La fórmula está en la columna J de "Desarrollos" por si quieres cambiar el umbral.
A5: Familias | B5: Original vs. variante es orientativo, como pediste. Se han añadido familias que el temario formaliza aunque no se llamen "modelo" (curva de Phillips, teoría cuantitativa, paridades, equivalencia ricardiana, dinámica de la deuda, monopolio, competencia perfecta...).
A6: Fuera de alcance | B6: Formalización que no es un modelo económico (teoría del consumidor/productor y dualidad, contabilidad nacional y empresarial, VAN/TIR, índices de progresividad, teoremas del bienestar, herramientas de optimización dinámica). Está listada en "Formalización sin modelo" por si quieres que alguna se trate como modelo.
A7: Límite técnico | B7: Los desarrollos solo gráficos (PNG) o con matemática únicamente en línea ($...$) no se detectan. Si un tema desarrolla un modelo así, aparecerá como ausente.
A8: Datos | B8: Repos actualizados (git pull) el 02/10/2026 a las 13:10. 612 bloques atribuidos a 96 familias en 56 temas; 34 familias se desarrollan en 2 o más temas.
A9: Incidencia | B9: Tras tu corrección queda un título erróneo: el main.tex de Tema-3.B.34 dice "Tema 4.B.34".
