Workbook

Sheet Resumen
A1: Modelos del temario TCEE y temas en los que aparecen (original o variante)
A2: Fuente: github.com/OposicionTCEE (107 repos, clonados el 02/10/2026). Detección automática por patrones + revisión manual de ambigüedades; ver hoja "Notas". Nº de temas y desglose por bloque se calculan con fórmulas sobre la hoja "Matriz".
A4: Área | B4: Modelo (versión original) | C4: Autor(es) y año | D4: Nº temas | E4: Bloque 3.A | F4: Bloque 3.B | G4: Bloque 4.B | H4: Temas donde aparece (original o variante) | I4: Temas donde se desarrolla (D) | J4: Variantes detectadas | K4: Temas solo por variante
A5: Pensamiento económico | B5: Tableau économique | C5: Quesnay (1758) | D5: =COUNTA(Matriz!D2:CV2) -> 4 | E5: =SUMPRODUCT((LEFT(Matriz!$D$1:$CV$1,3)="3.A")*(Matriz!D2:CV2<>"")) -> 3 | F5: =SUMPRODUCT((LEFT(Matriz!$D$1:$CV$1,3)="3.B")*(Matriz!D2:CV2<>"")) -> 0 | G5: =SUMPRODUCT((LEFT(Matriz!$D$1:$CV$1,3)="4.B")*(Matriz!D2:CV2<>"")) -> 1 | H5: 3.A.2, 3.A.5, 3.A.31, 4.B.13 | I5: — | J5: — | K5: —
A6: Pensamiento económico | B6: Modelo malthusiano de población | C6: Malthus (1798) | D6: =COUNTA(Matriz!D3:CV3) -> 1 | E6: =SUMPRODUCT((LEFT(Matriz!$D$1:$CV$1,3)="3.A")*(Matriz!D3:CV3<>"")) -> 1 | F6: =SUMPRODUCT((LEFT(Matriz!$D$1:$CV$1,3)="3.B")*(Matriz!D3:CV3<>"")) -> 0 | G6: =SUMPRODUCT((LEFT(Matriz!$D$1:$CV$1,3)="4.B")*(Matriz!D3:CV3<>"")) -> 0 | H6: 3.A.2 | I6: — | J6: — | K6: —
A7: Pensamiento económico | B7: Economía de Robinson Crusoe | C7: Tradición neoclásica | D7: =COUNTA(Matriz!D4:CV4) -> 3 | E7: =SUMPRODUCT((LEFT(Matriz!$D$1:$CV$1,3)="3.A")*(Matriz!D4:CV4<>"")) -> 3 | F7: =SUMPRODUCT((LEFT(Matriz!$D$1:$CV$1,3)="3.B")*(Matriz!D4:CV4<>"")) -> 0 | G7: =SUMPRODUCT((LEFT(Matriz!$D$1:$CV$1,3)="4.B")*(Matriz!D4:CV4<>"")) -> 0 | H7: 3.A.3, 3.A.29, 3.A.35 | I7: — | J7: — | K7: —
A8: Microeconomía | B8: Utilidad esperada | C8: von Neumann-Morgenstern (1944) | D8: =COUNTA(Matriz!D5:CV5) -> 12 | E8: =SUMPRODUCT((LEFT(Matriz!$D$1:$CV$1,3)="3.A")*(Matriz!D5:CV5<>"")) -> 10 | F8: =SUMPRODUCT((LEFT(Matriz!$D$1:$CV$1,3)="3.B")*(Matriz!D5:CV5<>"")) -> 2 | G8: =SUMPRODUCT((LEFT(Matriz!$D$1:$CV$1,3)="4.B")*(Matriz!D5:CV5<>"")) -> 0 | H8: 3.A.1, 3.A.3, 3.A.7, 3.A.8, 3.A.10, 3.A.13, 3.A.15, 3.A.19, 3.A.29, 3.A.42, 3.B.13, 3.B.14 | I8: 3.A.10 | J8: Múltiples previos / maxmin (Gilboa-Schmeidler); Utilidad subjetiva esperada (Savage) | K8: —
A9: Microeconomía | B9: Teoría prospectiva | C9: Kahneman-Tversky (1979) | D9: =COUNTA(Matriz!D6:CV6) -> 4 | E9: =SUMPRODUCT((LEFT(Matriz!$D$1:$CV$1,3)="3.A")*(Matriz!D6:CV6<>"")) -> 3 | F9: =SUMPRODUCT((LEFT(Matriz!$D$1:$CV$1,3)="3.B")*(Matriz!D6:CV6<>"")) -> 1 | G9: =SUMPRODUCT((LEFT(Matriz!$D$1:$CV$1,3)="4.B")*(Matriz!D6:CV6<>"")) -> 0 | H9: 3.A.1, 3.A.10, 3.A.33, 3.B.13 | I9: 3.A.10 | J9: — | K9: —
A10: Microeconomía | B10: Descuento cuasi-hiperbólico | C10: Laibson (1997) | D10: =COUNTA(Matriz!D7:CV7) -> 3 | E10: =SUMPRODUCT((LEFT(Matriz!$D$1:$CV$1,3)="3.A")*(Matriz!D7:CV7<>"")) -> 2 | F10: =SUMPRODUCT((LEFT(Matriz!$D$1:$CV$1,3)="3.B")*(Matriz!D7:CV7<>"")) -> 0 | G10: =SUMPRODUCT((LEFT(Matriz!$D$1:$CV$1,3)="4.B")*(Matriz!D7:CV7<>"")) -> 1 | H10: 3.A.1, 3.A.29, 4.B.24 | I10: — | J10: — | K10: —
A11: Microeconomía | B11: Asignación del tiempo | C11: Becker (1965) | D11: =COUNTA(Matriz!D8:CV8) -> 1 | E11: =SUMPRODUCT((LEFT(Matriz!$D$1:$CV$1,3)="3.A")*(Matriz!D8:CV8<>"")) -> 1 | F11: =SUMPRODUCT((LEFT(Matriz!$D$1:$CV$1,3)="3.B")*(Matriz!D8:CV8<>"")) -> 0 | G11: =SUMPRODUCT((LEFT(Matriz!$D$1:$CV$1,3)="4.B")*(Matriz!D8:CV8<>"")) -> 0 | H11: 3.A.25 | I11: 3.A.25 | J11: — | K11: —
A12: Microeconomía | B12: Elección ocio-consumo (oferta de trabajo neoclásica) | C12: Robbins (1930) / tradición neoclásica | D12: =COUNTA(Matriz!D9:CV9) -> 7 | E12: =SUMPRODUCT((LEFT(Matriz!$D$1:$CV$1,3)="3.A")*(Matriz!D9:CV9<>"")) -> 7 | F12: =SUMPRODUCT((LEFT(Matriz!$D$1:$CV$1,3)="3.B")*(Matriz!D9:CV9<>"")) -> 0 | G12: =SUMPRODUCT((LEFT(Matriz!$D$1:$CV$1,3)="4.B")*(Matriz!D9:CV9<>"")) -> 0 | H12: 3.A.3, 3.A.6, 3.A.7, 3.A.22, 3.A.25, 3.A.35, 3.A.41 | I12: 3.A.6 | J12: — | K12: —
A13: Microeconomía | B13: Competencia monopolística | C13: Chamberlin (1933) | D13: =COUNTA(Matriz!D10:CV10) -> 15 | E13: =SUMPRODUCT((LEFT(Matriz!$D$1:$CV$1,3)="3.A")*(Matriz!D10:CV10<>"")) -> 12 | F13: =SUMPRODUCT((LEFT(Matriz!$D$1:$CV$1,3)="3.B")*(Matriz!D10:CV10<>"")) -> 3 | G13: =SUMPRODUCT((LEFT(Matriz!$D$1:$CV$1,3)="4.B")*(Matriz!D10:CV10<>"")) -> 0 | H13: 3.A.4, 3.A.7, 3.A.15, 3.A.17, 3.A.18, 3.A.19, 3.A.20, 3.A.28, 3.A.37, 3.A.41, 3.A.42, 3.A.44, 3.B.6, 3.B.7, 3.B.10 | I13: 3.A.7, 3.A.18, 3.A.19, 3.B.6, 3.B.7 | J13: Dixit-Stiglitz (1977) | K13: 3.A.20
A14: Microeconomía | B14: Duopolio de Cournot | C14: Cournot (1838) | D14: =COUNTA(Matriz!D11:CV11) -> 2 | E14: =SUMPRODUCT((LEFT(Matriz!$D$1:$CV$1,3)="3.A")*(Matriz!D11:CV11<>"")) -> 2 | F14: =SUMPRODUCT((LEFT(Matriz!$D$1:$CV$1,3)="3.B")*(Matriz!D11:CV11<>"")) -> 0 | G14: =SUMPRODUCT((LEFT(Matriz!$D$1:$CV$1,3)="4.B")*(Matriz!D11:CV11<>"")) -> 0 | H14: 3.A.18, 3.A.19 | I14: 3.A.18, 3.A.19 | J14: Kreps-Scheinkman (1983) | K14: —
A15: Microeconomía | B15: Duopolio de Bertrand | C15: Bertrand (1883) | D15: =COUNTA(Matriz!D12:CV12) -> 2 | E15: =SUMPRODUCT((LEFT(Matriz!$D$1:$CV$1,3)="3.A")*(Matriz!D12:CV12<>"")) -> 2 | F15: =SUMPRODUCT((LEFT(Matriz!$D$1:$CV$1,3)="3.B")*(Matriz!D12:CV12<>"")) -> 0 | G15: =SUMPRODUCT((LEFT(Matriz!$D$1:$CV$1,3)="4.B")*(Matriz!D12:CV12<>"")) -> 0 | H15: 3.A.18, 3.A.19 | I15: 3.A.18, 3.A.19 | J15: Bertrand-Edgeworth (restricciones de capacidad) | K15: —
A16: Microeconomía | B16: Liderazgo de Stackelberg | C16: von Stackelberg (1934) | D16: =COUNTA(Matriz!D13:CV13) -> 3 | E16: =SUMPRODUCT((LEFT(Matriz!$D$1:$CV$1,3)="3.A")*(Matriz!D13:CV13<>"")) -> 1 | F16: =SUMPRODUCT((LEFT(Matriz!$D$1:$CV$1,3)="3.B")*(Matriz!D13:CV13<>"")) -> 2 | G16: =SUMPRODUCT((LEFT(Matriz!$D$1:$CV$1,3)="4.B")*(Matriz!D13:CV13<>"")) -> 0 | H16: 3.A.19, 3.B.8, 3.B.16 | I16: 3.A.19 | J16: — | K16: —
... A144: Macroeconomía abierta | B144: Chartistas y fundamentalistas (agentes heterogéneos en divisas) | C144: Frankel-Froot (1990) / De Grauwe-Grimaldi (2006) | D144: =COUNTA(Matriz!D141:CV141) -> 4 | E144: =SUMPRODUCT((LEFT(Matriz!$D$1:$CV$1,3)="3.A")*(Matriz!D141:CV141<>"")) -> 1 | F144: =SUMPRODUCT((LEFT(Matriz!$D$1:$CV$1,3)="3.B")*(Matriz!D141:CV141<>"")) -> 3 | G144: =SUMPRODUCT((LEFT(Matriz!$D$1:$CV$1,3)="4.B")*(Matriz!D141:CV141<>"")) -> 0 | H144: 3.A.32, 3.B.13, 3.B.14, 3.B.16 | I144: 3.B.14 | J144: De Grauwe-Grimaldi (2006) | K144: 3.B.16

Sheet Matriz
A1: Área | B1: Modelo (versión original) | C1: Nº temas | D1: 3.A.1 | E1: 3.A.2 | F1: 3.A.3 | G1: 3.A.4 | H1: 3.A.5 | I1: 3.A.6 | J1: 3.A.7 | K1: 3.A.8 | L1: 3.A.9 | M1: 3.A.10 | N1: 3.A.11 | O1: 3.A.12 | P1: 3.A.13 | Q1: 3.A.15 | R1: 3.A.16 | S1: 3.A.17 | T1: 3.A.18 | U1: 3.A.19 | V1: 3.A.20 | W1: 3.A.21 | X1: 3.A.22 | Y1: 3.A.23 | Z1: 3.A.24 | AA1: 3.A.25 | AB1: 3.A.26 | AC1: 3.A.27 | AD1: 3.A.28 | AE1: 3.A.29 | AF1: 3.A.30 | AG1: 3.A.31 | AH1: 3.A.32 | AI1: 3.A.33 | AJ1: 3.A.34 | AK1: 3.A.35 | AL1: 3.A.36 | AM1: 3.A.37 | AN1: 3.A.38 | AO1: 3.A.39 | AP1: 3.A.40 | AQ1: 3.A.41 | AR1: 3.A.42 | AS1: 3.A.43 | AT1: 3.A.44 | AU1: 3.A.45 | AV1: 3.B.2 | AW1: 3.B.3 | AX1: 3.B.4 | AY1: 3.B.5 | AZ1: 3.B.6 | BA1: 3.B.7 | BB1: 3.B.8 | BC1: 3.B.9 | BD1: 3.B.10 | BE1: 3.B.11 | BF1: 3.B.12 | BG1: 3.B.13 | BH1: 3.B.14 | BI1: 3.B.15 | BJ1: 3.B.16 | BK1: 3.B.17 | BL1: 3.B.18 | BM1: 3.B.19 | BN1: 3.B.20 | BO1: 3.B.21 | BP1: 3.B.22 | BQ1: 3.B.23 | BR1: 3.B.25 | BS1: 3.B.26 | BT1: 3.B.27 | BU1: 3.B.28 | BV1: 3.B.29 | BW1: 3.B.31 | BX1: 3.B.32 | BY1: 3.B.33 | BZ1: 3.B.34 | CA1: 3.B.35 | CB1: 3.B.39 | CC1: 3.B.40 | CD1: 3.B.43 | CE1: 3.B.45 | CF1: 4.B.8 | CG1: 4.B.9 | CH1: 4.B.10 | CI1: 4.B.11 | CJ1: 4.B.12 | CK1: 4.B.13 | CL1: 4.B.14 | CM1: 4.B.15 | CN1: 4.B.16 | CO1: 4.B.17 | CP1: 4.B.19 | CQ1: 4.B.20 | CR1: 4.B.21 | CS1: 4.B.23 | CT1: 4.B.24 | CU1: 4.B.25 | CV1: 4.B.26
A2: Pensamiento económico | B2: Tableau économique | C2: =COUNTA(D2:CV2) -> 4 | E2: M | H2: M | AG2: T | CK2: T
A3: Pensamiento económico | B3: Modelo malthusiano de población | C3: =COUNTA(D3:CV3) -> 1 | E3: M
A4: Pensamiento económico | B4: Economía de Robinson Crusoe | C4: =COUNTA(D4:CV4) -> 3 | F4: T | AE4: M | AK4: M
A5: Microeconomía | B5: Utilidad esperada | C5: =COUNTA(D5:CV5) -> 12 | D5: T | F5: M | J5: M | K5: M | M5: D | P5: T | Q5: M | U5: M | AE5: M | AR5: M | BG5: M | BH5: M
A6: Microeconomía | B6: Teoría prospectiva | C6: =COUNTA(D6:CV6) -> 4 | D6: T | M6: D | AI6: T | BG6: T
A7: Microeconomía | B7: Descuento cuasi-hiperbólico | C7: =COUNTA(D7:CV7) -> 3 | D7: T | AE7: T | CT7: T
A8: Microeconomía | B8: Asignación del tiempo | C8: =COUNTA(D8:CV8) -> 1 | AA8: D
A9: Microeconomía | B9: Elección ocio-consumo (oferta de trabajo neoclásica) | C9: =COUNTA(D9:CV9) -> 7 | F9: M | I9: D | J9: T | X9: M | AA9: T | AK9: T | AQ9: M
A10: Microeconomía | B10: Competencia monopolística | C10: =COUNTA(D10:CV10) -> 15 | G10: T | J10: D | Q10: T | S10: M | T10: D | U10: D | V10: M | AD10: M | AM10: M | AQ10: T | AR10: T | AT10: M | AZ10: D | BA10: D | BD10: T
A11: Microeconomía | B11: Duopolio de Cournot | C11: =COUNTA(D11:CV11) -> 2 | T11: D | U11: D
A12: Microeconomía | B12: Duopolio de Bertrand | C12: =COUNTA(D12:CV12) -> 2 | T12: D | U12: D
A13: Microeconomía | B13: Liderazgo de Stackelberg | C13: =COUNTA(D13:CV13) -> 3 | U13: D | BB13: T | BJ13: M
A14: Microeconomía | B14: Ciudad lineal (diferenciación espacial) | C14: =COUNTA(D14:CV14) -> 3 | I14: M | T14: D | U14: T
A15: Microeconomía | B15: Modelo de la telaraña | C15: =COUNTA(D15:CV15) -> 1 | R15: D
A16: Microeconomía | B16: Precio límite | C16: =COUNTA(D16:CV16) -> 1 | U16: T
A17: Microeconomía | B17: Mercados disputables | C17: =COUNTA(D17:CV17) -> 2 | Q17: T | CM17: M
A18: Microeconomía | B18: Maximización de ventas | C18: =COUNTA(D18:CV18) -> 1 | Q18: M
A19: Microeconomía | B19: Maximización del crecimiento de la empresa | C19: =COUNTA(D19:CV19) -> 1 | Q19: T
A20: Microeconomía | B20: Preferencia por el gasto (discrecionalidad directiva) | C20: =COUNTA(D20:CV20) -> 1 | Q20: M
A21: Microeconomía | B21: Principal-agente | C21: =COUNTA(D21:CV21) -> 11 | P21: D | Q21: T | Y21: T | AC21: M | AI21: M | AJ21: M | AW21: T | BS21: M | BT21: M | CL21: T | CM21: M
A22: Microeconomía | B22: Mercado de limones (selección adversa) | C22: =COUNTA(D22:CV22) -> 11 | D22: M | J22: D | M22: M | P22: D | AC22: M | BJ22: M | BS22: M | CH22: M | CJ22: M | CM22: D | CT22: T
A23: Microeconomía | B23: Filtrado en mercado de seguros | C23: =COUNTA(D23:CV23) -> 3 | M23: T | P23: D | CT23: T
A24: Microeconomía | B24: Señalización en el mercado de trabajo | C24: =COUNTA(D24:CV24) -> 2 | P24: D | AA24: T
A25: Microeconomía | B25: Equilibrio general walrasiano / Arrow-Debreu | C25: =COUNTA(D25:CV25) -> 10 | D25: T | I25: M | J25: M | M25: T | W25: D | Y25: T | Z25: M | AC25: M | AE25: M | AR25: M
A26: Microeconomía | B26: Tablas input-output | C26: =COUNTA(D26:CV26) -> 7 | H26: T | N26: T | AF26: T | AG26: D | BC26: M | BL26: D | BX26: M
A27: Microeconomía | B27: Equilibrio general computable (CGE) | C27: =COUNTA(D27:CV27) -> 3 | W27: T | BC27: M | BD27: D
A28: Microeconomía | B28: Análisis envolvente de datos (DEA) | C28: =COUNTA(D28:CV28) -> 4 | G28: T | O28: D | AH28: T | BH28: T
A29: Microeconomía | B29: Frontera estocástica (SFA) | C29: =COUNTA(D29:CV29) -> 1 | O29: D
A30: Regulación | B30: Sobrecapitalización bajo regulación por tasa de rendimiento | C30: =COUNTA(D30:CV30) -> 1 | V30: T
A31: Regulación | B31: Regulación con información asimétrica | C31: =COUNTA(D31:CV31) -> 2 | Q31: T | V31: D
A32: Regulación | B32: Teoría de la captura del regulador | C32: =COUNTA(D32:CV32) -> 4 | Q32: M | V32: D | Y32: T | CB32: M
A33: Sector público | B33: Imposición / tarificación óptima de Ramsey | C33: =COUNTA(D33:CV33) -> 10 | D33: M | V33: D | X33: M | Y33: M | AN33: T | AO33: M | CH33: M | CI33: D | CK33: D | CQ33: T
A34: Sector público | B34: Imposición óptima sobre la renta | C34: =COUNTA(D34:CV34) -> 10 | D34: M | P34: M | BU34: M | CH34: M | CI34: D | CJ34: M | CK34: D | CN34: T | CQ34: T | CS34: M
A35: Sector público | B35: Imposición óptima del capital (tipo cero a largo plazo) | C35: =COUNTA(D35:CV35) -> 4 | CI35: D | CJ35: D | CK35: M | CN35: M
A36: Sector público | B36: Incidencia impositiva en equilibrio general | C36: =COUNTA(D36:CV36) -> 2 | CF36: D | CJ36: M
A37: Sector público | B37: Administración tributaria óptima | C37: =COUNTA(D37:CV37) -> 1 | CI37: T
A38: Sector público | B38: Evasión fiscal | C38: =COUNTA(D38:CV38) -> 3 | M38: M | X38: M | CI38: T
A39: Sector público | B39: Imposición y asunción de riesgos | C39: =COUNTA(D39:CV39) -> 1 | CH39: D
A40: Sector público | B40: Votar con los pies | C40: =COUNTA(D40:CV40) -> 6 | Y40: T | CJ40: M | CL40: D | CO40: T | CP40: T | CU40: D
A41: Sector público | B41: Teorema de la descentralización | C41: =COUNTA(D41:CV41) -> 6 | CJ41: T | CL41: D | CP41: T | CR41: T | CT41: T | CU41: D
A42: Sector público | B42: Teoría de los clubes | C42: =COUNTA(D42:CV42) -> 2 | Y42: M | CL42: D
A43: Sector público | B43: Burocracia maximizadora del presupuesto | C43: =COUNTA(D43:CV43) -> 5 | Q43: T | CL43: M | CM43: D | CT43: T | CU43: M
A44: Sector público | B44: Leviatán | C44: =COUNTA(D44:CV44) -> 4 | CJ44: D | CK44: D | CL44: D | CU44: T
A45: Sector público | B45: Votante mediano | C45: =COUNTA(D45:CV45) -> 6 | Z45: M | AO45: M | BA45: M | CL45: T | CT45: D | CU45: M
A46: Sector público | B46: Bienes públicos: provisión eficiente | C46: =COUNTA(D46:CV46) -> 4 | Y46: D | Z46: M | CJ46: D | CL46: M
A47: Sector público | B47: Ciclo político | C47: =COUNTA(D47:CV47) -> 4 | I47: M | V47: M | CR47: M | CT47: M
A48: Macroeconomía | B48: Modelo keynesiano simple (renta-gasto / aspa keynesiana) | C48: =COUNTA(D48:CV48) -> 2 | AP48: D | BH48: D
A49: Macroeconomía | B49: IS-LM | C49: =COUNTA(D49:CV49) -> 12 | G49: M | H49: D | I49: T | J49: T | AD49: T | AK49: M | AL49: M | AN49: T | AO49: T | AP49: T | BI49: M | BM49: M
A50: Macroeconomía | B50: Oferta y demanda agregadas | C50: =COUNTA(D50:CV50) -> 2 | G50: M | AR50: M
A51: Macroeconomía | B51: Modelos de desequilibrio | C51: =COUNTA(D51:CV51) -> 2 | G51: T | W51: M
A52: Macroeconomía | B52: Ciclo Real (RBC) | C52: =COUNTA(D52:CV52) -> 8 | D52: M | I52: D | J52: M | AA52: M | AE52: M | AH52: T | AP52: D | AR52: D
A53: Macroeconomía | B53: Inconsistencia temporal de la política | C53: =COUNTA(D53:CV53) -> 22 | D53: M | I53: D | V53: D | Y53: D | AE53: M | AI53: M | AL53: T | AP53: M | AV53: M | BF53: M | BI53: D | BJ53: T | BK53: M | BM53: T | BS53: M | BT53: T | BY53: M | CI53: T | CR53: T | CT53: D | CU53: T | CV53: T
A54: Macroeconomía | B54: Islas de Lucas (información imperfecta) | C54: =COUNTA(D54:CV54) -> 4 | D54: M | I54: D | J54: M | AB54: M
A55: Macroeconomía | B55: Contratos escalonados (rigidez nominal) | C55: =COUNTA(D55:CV55) -> 6 | J55: D | AD55: T | AH55: T | AM55: M | AQ55: T | AR55: M
A56: Macroeconomía | B56: Costes de menú | C56: =COUNTA(D56:CV56) -> 6 | I56: T | J56: D | AJ56: M | AK56: M | AQ56: M | AR56: M
A57: Macroeconomía | B57: Información rígida | C57: =COUNTA(D57:CV57) -> 1 | J57: T
A58: Macroeconomía | B58: Nuevo keynesiano de tres ecuaciones (NEK-2) | C58: =COUNTA(D58:CV58) -> 11 | J58: D | AD58: D | AH58: D | AK58: M | AM58: D | AN58: D | AP58: D | AQ58: D | AR58: D | BF58: M | BM58: D
A59: Macroeconomía | B59: DSGE | C59: =COUNTA(D59:CV59) -> 19 | D59: M | G59: M | H59: M | I59: T | J59: D | V59: T | W59: M | AD59: T | AE59: M | AH59: T | AK59: T | AM59: M | AQ59: M | AR59: D | BF59: M | BR59: M | BW59: D | CD59: T | CO59: M
A60: Macroeconomía | B60: Modelos basados en agentes (ABM) | C60: =COUNTA(D60:CV60) -> 5 | D60: M | J60: M | AE60: D | AH60: D | BH60: D
A61: Macroeconomía | B61: Modelos VAR | C61: =COUNTA(D61:CV61) -> 7 | G61: M | I61: T | AH61: M | AK61: D | AM61: D | AR61: M | BI61: T
A62: Macroeconomía | B62: Modelos ARMA/ARIMA | C62: =COUNTA(D62:CV62) -> 3 | AE62: M | AR62: T | BS62: M
A63: Macroeconomía | B63: Modelos ARCH/GARCH | C63: =COUNTA(D63:CV63) -> 2 | BS63: T | BT63: M
A64: Macroeconomía | B64: Renta permanente | C64: =COUNTA(D64:CV64) -> 17 | H64: D | M64: T | AE64: T | AI64: D | AK64: D | AM64: M | AN64: M | AO64: M | AP64: T | AQ64: M | BH64: M | BV64: M | CH64: T | CJ64: D | CK64: M | CM64: M | CV64: M
A65: Macroeconomía | B65: Ciclo vital | C65: =COUNTA(D65:CV65) -> 6 | H65: M | I65: M | AA65: M | AI65: D | AW65: M | CP65: M
A66: Macroeconomía | B66: Renta relativa | C66: =COUNTA(D66:CV66) -> 4 | AI66: T | BH66: M | CT66: T | CU66: M
A67: Macroeconomía | B67: Acelerador de la inversión | C67: =COUNTA(D67:CV67) -> 9 | G67: M | H67: T | J67: M | AD67: T | AQ67: T | AR67: M | BK67: M | BN67: M | CB67: M
A68: Macroeconomía | B68: Teoría neoclásica de la inversión | C68: =COUNTA(D68:CV68) -> 5 | I68: T | AA68: M | AJ68: D | CF68: M | CG68: M
A69: Macroeconomía | B69: q de Tobin | C69: =COUNTA(D69:CV69) -> 3 | G69: M | H69: M | AJ69: D
A70: Macroeconomía | B70: Opciones reales de inversión | C70: =COUNTA(D70:CV70) -> 4 | AJ70: D | AV70: D | AX70: D | BR70: M
A71: Macroeconomía | B71: Acelerador financiero | C71: =COUNTA(D71:CV71) -> 6 | AH71: M | AJ71: M | AM71: D | AQ71: T | AR71: D | BS71: M
A72: Macroeconomía | B72: Demanda de dinero por inventario | C72: =COUNTA(D72:CV72) -> 2 | AK72: D | AQ72: M
A73: Macroeconomía | B73: Dinero en la función de utilidad (MIU) | C73: =COUNTA(D73:CV73) -> 3 | W73: T | AK73: D | AR73: T
A74: Macroeconomía | B74: Cash-in-advance (CIA) | C74: =COUNTA(D74:CV74) -> 4 | I74: M | W74: T | AK74: D | AQ74: M
A75: Macroeconomía | B75: Hiperinflación | C75: =COUNTA(D75:CV75) -> 2 | H75: T | AQ75: D
A76: Macroeconomía | B76: Aritmética monetarista desagradable | C76: =COUNTA(D76:CV76) -> 2 | I76: T | CV76: T
A77: Macroeconomía | B77: Elección del instrumento de política monetaria | C77: =COUNTA(D77:CV77) -> 2 | AL77: D | BJ77: M
A78: Macroeconomía | B78: Suavización impositiva | C78: =COUNTA(D78:CV78) -> 5 | AK78: M | AM78: M | AN78: M | CU78: M | CV78: M
A79: Mercado de trabajo | B79: Salarios de eficiencia | C79: =COUNTA(D79:CV79) -> 5 | D79: M | I79: M | J79: T | P79: T | AC79: D
A80: Mercado de trabajo | B80: Insiders-outsiders | C80: =COUNTA(D80:CV80) -> 2 | AC80: D | AD80: D
A81: Mercado de trabajo | B81: Monopolio sindical | C81: =COUNTA(D81:CV81) -> 3 | AA81: M | AC81: D | BJ81: T
A82: Mercado de trabajo | B82: Búsqueda y emparejamiento (DMP) | C82: =COUNTA(D82:CV82) -> 5 | J82: M | Q82: M | AB82: D | AD82: D | BD82: M
A83: Mercado de trabajo | B83: NAIRU / WS-PS | C83: =COUNTA(D83:CV83) -> 2 | AD83: T | AQ83: T
A84: Crecimiento | B84: Harrod-Domar | C84: =COUNTA(D84:CV84) -> 4 | G84: T | H84: M | BV84: M | CV84: M
A85: Crecimiento | B85: Solow-Swan | C85: =COUNTA(D85:CV85) -> 4 | AS85: D | AT85: T | AU85: T | BJ85: M
A86: Crecimiento | B86: Ramsey-Cass-Koopmans | C86: =COUNTA(D86:CV86) -> 8 | I86: M | W86: M | AE86: D | AK86: T | AR86: T | AS86: D | BU86: T | BW86: T
A87: Crecimiento | B87: Generaciones solapadas | C87: =COUNTA(D87:CV87) -> 6 | W87: M | AE87: D | AK87: D | AN87: D | AO87: M | CT87: T
A88: Crecimiento | B88: Modelo AK | C88: =COUNTA(D88:CV88) -> 6 | S88: M | AN88: D | AP88: M | AT88: D | BO88: M | BU88: M
A89: Crecimiento | B89: Capital humano | C89: =COUNTA(D89:CV89) -> 4 | K89: M | L89: M | AK89: M | AT89: T
A90: Crecimiento | B90: Expansión de variedades (I+D) | C90: =COUNTA(D90:CV90) -> 3 | J90: M | AT90: D | CB90: M
A91: Crecimiento | B91: Escalera de calidad (destrucción creadora) | C91: =COUNTA(D91:CV91) -> 2 | Q91: M | AT91: M
A92: Desarrollo | B92: Gran impulso (big push) | C92: =COUNTA(D92:CV92) -> 3 | BC92: M | BL92: M | CA92: M
A93: Desarrollo | B93: Centro-periferia (estructuralismo) | C93: =COUNTA(D93:CV93) -> 5 | BB93: M | BC93: T | BD93: M | BX93: M | CC93: M
A94: Desarrollo | B94: Dos brechas | C94: =COUNTA(D94:CV94) -> 3 | N94: M | AG94: D | BV94: T
A95: Comercio internacional | B95: Modelo ricardiano | C95: =COUNTA(D95:CV95) -> 4 | E95: T | AY95: D | AZ95: M | BA95: T
A96: Comercio internacional | B96: Factores específicos | C96: =COUNTA(D96:CV96) -> 3 | AQ96: M | AY96: D | BL96: M
A97: Comercio internacional | B97: Heckscher-Ohlin | C97: =COUNTA(D97:CV97) -> 5 | D97: M | AY97: D | AZ97: T | BB97: M | BL97: T
A98: Comercio internacional | B98: Nueva teoría del comercio (rendimientos crecientes) | C98: =COUNTA(D98:CV98) -> 6 | AY98: M | AZ98: D | BA98: T | BD98: T | BJ98: M | BK98: M
A99: Comercio internacional | B99: Empresas heterogéneas | C99: =COUNTA(D99:CV99) -> 9 | D99: M | AY99: T | AZ99: D | BA99: D | BB99: M | BC99: M | BD99: M | BH99: T | BJ99: T
A100: Comercio internacional | B100: Modelo de gravedad | C100: =COUNTA(D100:CV100) -> 7 | D100: M | AZ100: D | BA100: M | BD100: D | BI100: M | BJ100: T | BL100: T
...

Sheet Detalle
A1: Área | B1: Modelo (versión original) | C1: Forma detectada | D1: Tema | E1: Título del tema | F1: Nº menciones | G1: En epígrafe | H1: Intensidad | I1: Expresiones encontradas | J1: Contexto (1er fragmento)
A2: Pensamiento económico | B2: Tableau économique | C2: Original | D2: 3.A.2 | E2: Los economistas clásicos y MARX | F2: 1 | G2: — | H2: Mención | I2: QUESNAY | J2: …ir el pensamiento economico de MALTHUS Falta incluir los antecedentes historicos, en particular: fisiocratas (QUESNAY) y mercantilistas (UK) arabic page 1 Introduccion En primer lugar, podriamos preguntarnos porque es important…
A3: Pensamiento económico | B3: Tableau économique | C3: Original | D3: 3.A.5 | E3: La síntesis neoclásica | F3: 1 | G3: — | H3: Mención | I3: QUESNAY | J3: …ntre ellos destacaron otrora los ingleses W. PETTY, GREGORY KING, JEVONS, EDGEWORTH y MARSHALL; los franceses QUESNAY, COURNOT; el suizo DANIEL BERNOULLI; el italiano PARETO; el aleman J.H. VON THUNEN y el norteamericano FISHER…
A4: Pensamiento económico | B4: Tableau économique | C4: Original | D4: 3.A.31 | E4: Análisis de las tablas Input-Output | F4: 2 | G4: — | H4: Tratado | I4: QUESNAY; Quesnay | J4: …hombres de negocios, habian estudiado cuestiones concretas como los impuestos, el comercio o el dinero, pero QUESNAY, un medico familiarizado con la circulacion de la sangre, avanzo la idea del flujo circular del producto soci…
A5: Pensamiento económico | B5: Tableau économique | C5: Original | D5: 4.B.13 | E5: Teoría impositiva (VII): Imposición indirecta | F5: 2 | G5: — | H5: Tratado | I5: QUESNAY; Quesnay | J5: …propio vocabulario no nace con el, sino casi un siglo antes, en la Francia de los fisiocratas. La escuela de QUESNAY, convencida de que la tierra era la unica fuente autentica de riqueza y de que todo el resto de la actividad…
A6: Pensamiento económico | B6: Modelo malthusiano de población | C6: Original | D6: 3.A.2 | E6: Los economistas clásicos y MARX | F6: 1 | G6: — | H6: Mención | I6: modelo malthusiano | J6: …la tesis malthusiana con la doctrina del fondo de salarios se ha denominado ley de hierro de los salarios. El modelo malthusiano ha tenido muchas mas repercusiones de las que nunca imagino su autor. Los naturalistas britanicos CHARLES DAR…
A7: Pensamiento económico | B7: Economía de Robinson Crusoe | C7: Original | D7: 3.A.3 | E7: Los economistas neoclásicos | F7: 3 | G7: — | H7: Tratado | I7: Crusoe | J7: …EWORTH dos mapas completos de curvas de indiferencia, que en este caso se dan en el mundo aislado de Robinson Crusoe y su esclavo Viernes. Estos intercambian dos bienes, pero esos bienes son males para el otro: dinero (Viernes…
A8: Pensamiento económico | B8: Economía de Robinson Crusoe | C8: Original | D8: 3.A.29 | E8: Modelización dinámica de las tomas de decisiones | F8: 1 | G8: — | H8: Mención | I8: CRUSOE | J8: …os en una isla desierta con suficientes recursos para vivir y para reproducirse. Algo parecido a un modelo de CRUSOE pero con intencion de permanencia y sin posibilidad de salir de esta isla. Cada generacion de individuos tien…
A9: Pensamiento económico | B9: Economía de Robinson Crusoe | C9: Original | D9: 3.A.35 | E9: Teorías de la demanda de dinero | F9: 1 | G9: — | H9: Mención | I9: CRUSOE | J9: …os en una isla desierta con suficientes recursos para vivir y para reproducirse. Algo parecido a un modelo de CRUSOE pero con intencion de permanencia y sin posibilidad de salir de esta isla. Cada generacion de individuos tien…
A10: Microeconomía | B10: Utilidad esperada | C10: Original | D10: 3.A.1 | E10: Objeto y método de la ciencia económica | F10: 2 | G10: — | H10: Tratado | I10: VON NEUMANN; teoria de la utilidad esperada | J10: …s anos 50 en el Modelo ARROW-DEBREU, gracias a los aportes matematicos realizados en los anos 30's por WALD y VON NEUMANN. El documento de KENNETH ARROW y GERARD DEBREU Existence of an Equilibrium for a Competitive Economy , 1954,…
A11: Microeconomía | B11: Utilidad esperada | C11: Original | D11: 3.A.3 | E11: Los economistas neoclásicos | F11: 1 | G11: — | H11: Mención | I11: Von Neumann | J11: …RGENSTERN presento una esquematizacion rigurosa de una funcion de utilidad ordinal (el teorema de utilidad de Von Neumann-Morgenstern) en Theory of Games and Economic Behavior. Conclusion Recapitulacion Extensiones y relacion con o…
A12: Microeconomía | B12: Utilidad esperada | C12: Original | D12: 3.A.7 | E12: La nueva economía Keynesiana | F12: 1 | G12: — | H12: Mención | I12: funcion de utilidad esperada | J12: …banco central con la siguiente forma: La derivara traves de la aproximacion de TAYLOR de segundo orden de la funcion de utilidad esperada del agente representativo de la economia lo que resulta fundamental ya que esta no va a depender de funciones…
A13: Microeconomía | B13: Utilidad esperada | C13: Original | D13: 3.A.8 | E13: Teoría de la demanda del consumidor (I) | F13: 1 | G13: — | H13: Mención | I13: VON NEUMANN | J13: …a dualidad no es un teorema, sino un “principio”. Aunque la formalizacion matematica de esta teoria se debe a VON NEUMANN, que realizo grandes contribuciones a la programacion lineal (campo de las matematicas, en concreto del anali…
... A742: Macroeconomía abierta | B742: Chartistas y fundamentalistas (agentes heterogéneos en divisas) | C742: De Grauwe-Grimaldi (2006) | D742: 3.B.16 | E742: Teoría de la integración monetaria | F742: 2 | G742: — | H742: Tratado | I742: Grauwe y Grimaldi; GRAUWE y GRIMALDI | J742: …omportamiento gregario, generando gran volatilidad que, a su vez, se transmite a las economias nacionales (De Grauwe y Grimaldi, 2006). Sobre la base de estos argumentos, el nuevo MUNDELL paso a considerar la union monetaria como una for…

Sheet Temas
A1: Tema (repo) | B1: Título | C1: Nº modelos | D1: Modelos detectados | E1: Observación
A2: 3.A.1 | B2: Objeto y método de la ciencia económica | C2: =COUNTA(Matriz!D2:D141) -> 21 | D2: Utilidad esperada; Teoría prospectiva; Descuento cuasi-hiperbólico; Mercado de limones (selección adversa); Equilibrio general walrasiano / Arrow-Debreu; Imposición / tarificación óptima de Ramsey; Imposición óptima sobre la renta; Ciclo Real (RBC); Inconsistencia temporal de la política; Islas de Lucas (información imperfecta); DSGE; Modelos basados en agentes (ABM); Salarios de eficiencia; Heckscher-Ohlin; Empresas heterogéneas; Modelo de gravedad; Mecanismo flujo-especie-precio; Mundell-Fleming; Nueva macroeconomía de economía abierta (NOEM); Selección de carteras media-varianza; Inestabilidad financiera
A3: 3.A.2 | B3: Los economistas clásicos y MARX | C3: =COUNTA(Matriz!E2:E141) -> 5 | D3: Tableau économique; Modelo malthusiano de población; Modelo ricardiano; Mecanismo flujo-especie-precio; Enfoque de elasticidades
A4: 3.A.3 | B4: Los economistas neoclásicos | C4: =COUNTA(Matriz!F2:F141) -> 4 | D4: Economía de Robinson Crusoe; Utilidad esperada; Elección ocio-consumo (oferta de trabajo neoclásica); Irrelevancia de la estructura financiera
A5: 3.A.4 | B5: El pensamiento económico de KEYNES | C5: =COUNTA(Matriz!G2:G141) -> 12 | D5: Competencia monopolística; Análisis envolvente de datos (DEA); IS-LM; Oferta y demanda agregadas; Modelos de desequilibrio; DSGE; Modelos VAR; Acelerador de la inversión; q de Tobin; Harrod-Domar; Enfoque de elasticidades; Inestabilidad financiera
A6: 3.A.5 | B6: La síntesis neoclásica | C6: =COUNTA(Matriz!H2:H141) -> 14 | D6: Tableau économique; Tablas input-output; IS-LM; DSGE; Renta permanente; Ciclo vital; Acelerador de la inversión; q de Tobin; Hiperinflación; Harrod-Domar; Mundell-Fleming; Modelo monetario del tipo de cambio (precios flexibles); CAPM; Irrelevancia de la estructura financiera
A7: 3.A.6 | B7: La nueva macroeconomía clásica | C7: =COUNTA(Matriz!I2:I141) -> 18 | D7: Elección ocio-consumo (oferta de trabajo neoclásica); Ciudad lineal (diferenciación espacial); Equilibrio general walrasiano / Arrow-Debreu; Ciclo político; IS-LM; Ciclo Real (RBC); Inconsistencia temporal de la política; Islas de Lucas (información imperfecta); Costes de menú; DSGE; Modelos VAR; Ciclo vital; Teoría neoclásica de la inversión; Cash-in-advance (CIA); Aritmética monetarista desagradable; Salarios de eficiencia; Ramsey-Cass-Koopmans; Curva de tipos paramétrica
A8: 3.A.7 | B8: La nueva economía Keynesiana | C8: =COUNTA(Matriz!J2:J141) -> 19 | D8: Utilidad esperada; Elección ocio-consumo (oferta de trabajo neoclásica); Competencia monopolística; Mercado de limones (selección adversa); Equilibrio general walrasiano / Arrow-Debreu; IS-LM; Ciclo Real (RBC); Islas de Lucas (información imperfecta); Contratos escalonados (rigidez nominal); Costes de menú; Información rígida; Nuevo keynesiano de tres ecuaciones (NEK-2); DSGE; Modelos basados en agentes (ABM); Acelerador de la inversión; Salarios de eficiencia; Búsqueda y emparejamiento (DMP); Expansión de variedades (I+D); Racionamiento del crédito
A9: 3.A.8 | B9: Teoría de la demanda del consumidor (I) | C9: =COUNTA(Matriz!K2:K141) -> 2 | D9: Utilidad esperada; Capital humano
A10: 3.A.9 | B10: Teoría de la demanda del consumidor (II) | C10: =COUNTA(Matriz!L2:L141) -> 1 | D10: Capital humano
A11: 3.A.10 | B11: Teoría de la demanda del consumidor (III) | C11: =COUNTA(Matriz!M2:M141) -> 8 | D11: Utilidad esperada; Teoría prospectiva; Mercado de limones (selección adversa); Filtrado en mercado de seguros; Equilibrio general walrasiano / Arrow-Debreu; Evasión fiscal; Renta permanente; Selección de carteras media-varianza
A12: 3.A.11 | B12: Teoría de la Producción (I) | C12: =COUNTA(Matriz!N2:N141) -> 2 | D12: Tablas input-output; Dos brechas
A13: 3.A.12 | B13: Teoría de los costes | C13: =COUNTA(Matriz!O2:O141) -> 2 | D13: Análisis envolvente de datos (DEA); Frontera estocástica (SFA)
A14: 3.A.13 | B14: Economía de la información | C14: =COUNTA(Matriz!P2:P141) -> 7 | D14: Utilidad esperada; Principal-agente; Mercado de limones (selección adversa); Filtrado en mercado de seguros; Señalización en el mercado de trabajo; Imposición óptima sobre la renta; Salarios de eficiencia
A15: 3.A.15 | B15: Teoría de la demanda del consumidor (II) | C15: =COUNTA(Matriz!Q2:Q141) -> 13 | D15: Utilidad esperada; Competencia monopolística; Mercados disputables; Maximización de ventas; Maximización del crecimiento de la empresa; Preferencia por el gasto (discrecionalidad directiva); Principal-agente; Regulación con información asimétrica; Teoría de la captura del regulador; Burocracia maximizadora del presupuesto; Búsqueda y emparejamiento (DMP); Escalera de calidad (destrucción creadora); Paradigma ecléctico OLI | E15: El main.tex se titula "Tema 3.A.9"; revisar
A16: 3.A.16 | B16: Análisis de mercados (I) | C16: =COUNTA(Matriz!R2:R141) -> 1 | D16: Modelo de la telaraña
A17: 3.A.17 | B17: Análisis de mercados (II) | C17: =COUNTA(Matriz!S2:S141) -> 3 | D17: Competencia monopolística; Modelo AK; Modelo monetario del tipo de cambio (precios flexibles) | E17: El main.tex se titula "Tema 3.A.16"; revisar
A18: 3.A.18 | B18: Análisis de mercados (III) | C18: =COUNTA(Matriz!T2:T141) -> 4 | D18: Competencia monopolística; Duopolio de Cournot; Duopolio de Bertrand; Ciudad lineal (diferenciación espacial)
A19: 3.A.19 | B19: Análisis de mercados (IV) | C19: =COUNTA(Matriz!U2:U141) -> 7 | D19: Utilidad esperada; Competencia monopolística; Duopolio de Cournot; Duopolio de Bertrand; Liderazgo de Stackelberg; Ciudad lineal (diferenciación espacial); Precio límite
A20: 3.A.20 | B20: Regulación y Poder de mercado | C20: =COUNTA(Matriz!V2:V141) -> 8 | D20: Competencia monopolística; Sobrecapitalización bajo regulación por tasa de rendimiento; Regulación con información asimétrica; Teoría de la captura del regulador; Imposición / tarificación óptima de Ramsey; Ciclo político; Inconsistencia temporal de la política; DSGE
A21: 3.A.21 | B21: La Teoría del Equilibrio General | C21: =COUNTA(Matriz!W2:W141) -> 8 | D21: Equilibrio general walrasiano / Arrow-Debreu; Equilibrio general computable (CGE); Modelos de desequilibrio; DSGE; Dinero en la función de utilidad (MIU); Cash-in-advance (CIA); Ramsey-Cass-Koopmans; Generaciones solapadas
A22: 3.A.22 | B22: Economía del Bienestar (I) | C22: =COUNTA(Matriz!X2:X141) -> 4 | D22: Elección ocio-consumo (oferta de trabajo neoclásica); Imposición / tarificación óptima de Ramsey; Evasión fiscal; Uniones aduaneras: creación y desviación de comercio
A23: 3.A.23 | B23: Economía del Bienestar (II) | C23: =COUNTA(Matriz!Y2:Y141) -> 8 | D23: Principal-agente; Equilibrio general walrasiano / Arrow-Debreu; Teoría de la captura del regulador; Imposición / tarificación óptima de Ramsey; Votar con los pies; Teoría de los clubes; Bienes públicos: provisión eficiente; Inconsistencia temporal de la política
A24: 3.A.24 | B24: Economía del Bienestar (III) | C24: =COUNTA(Matriz!Z2:Z141) -> 3 | D24: Equilibrio general walrasiano / Arrow-Debreu; Votante mediano; Bienes públicos: provisión eficiente
A25: 3.A.25 | B25: La teoría neoclásica del mercado de trabajo | C25: =COUNTA(Matriz!AA2:AA141) -> 7 | D25: Asignación del tiempo; Elección ocio-consumo (oferta de trabajo neoclásica); Señalización en el mercado de trabajo; Ciclo Real (RBC); Ciclo vital; Teoría neoclásica de la inversión; Monopolio sindical
A26: 3.A.26 | B26: Extensiones a la Teoría del Mercado de Trabajo | C26: =COUNTA(Matriz!AB2:AB141) -> 3 | D26: Islas de Lucas (información imperfecta); Búsqueda y emparejamiento (DMP); Costes de ajuste (demanda dinámica de factores)
A27: 3.A.27 | B27: Determinación de salarios | C27: =COUNTA(Matriz!AC2:AC141) -> 6 | D27: Principal-agente; Mercado de limones (selección adversa); Equilibrio general walrasiano / Arrow-Debreu; Salarios de eficiencia; Insiders-outsiders; Monopolio sindical
A28: 3.A.28 | B28: La tasa natural de paro y de la NAIRU | C28: =COUNTA(Matriz!AD2:AD141) -> 9 | D28: Competencia monopolística; IS-LM; Contratos escalonados (rigidez nominal); Nuevo keynesiano de tres ecuaciones (NEK-2); DSGE; Acelerador de la inversión; Insiders-outsiders; Búsqueda y emparejamiento (DMP); NAIRU / WS-PS
A29: 3.A.29 | B29: Modelización dinámica de las tomas de decisiones | C29: =COUNTA(Matriz!AE2:AE141) -> 12 | D29: Economía de Robinson Crusoe; Utilidad esperada; Descuento cuasi-hiperbólico; Equilibrio general walrasiano / Arrow-Debreu; Ciclo Real (RBC); Inconsistencia temporal de la política; DSGE; Modelos basados en agentes (ABM); Modelos ARMA/ARIMA; Renta permanente; Ramsey-Cass-Koopmans; Generaciones solapadas
A30: 3.A.30 | B30: Magnitudes macroeconómicas y contabilidad nacional | C30: =COUNTA(Matriz!AF2:AF141) -> 1 | D30: Tablas input-output
A31: 3.A.31 | B31: Análisis de las tablas Input-Output | C31: =COUNTA(Matriz!AG2:AG141) -> 3 | D31: Tableau économique; Tablas input-output; Dos brechas
A32: 3.A.32 | B32: El modelo de oferta y demanda agregada | C32: =COUNTA(Matriz!AH2:AH141) -> 11 | D32: Análisis envolvente de datos (DEA); Ciclo Real (RBC); Contratos escalonados (rigidez nominal); Nuevo keynesiano de tres ecuaciones (NEK-2); DSGE; Modelos basados en agentes (ABM); Modelos VAR; Acelerador financiero; Mundell-Fleming; Nueva macroeconomía de economía abierta (NOEM); Chartistas y fundamentalistas (agentes heterogéneos en divisas)
A33: 3.A.33 | B33: Teorías de la demanda de consumo corriente | C33: =COUNTA(Matriz!AI2:AI141) -> 7 | D33: Teoría prospectiva; Principal-agente; Inconsistencia temporal de la política; Renta permanente; Ciclo vital; Renta relativa; Modelo monetario del tipo de cambio (precios flexibles)
A34: 3.A.34 | B34: Teorías de la inversión en bienes de equipo | C34: =COUNTA(Matriz!AJ2:AJ141) -> 8 | D34: Principal-agente; Costes de menú; Teoría neoclásica de la inversión; q de Tobin; Opciones reales de inversión; Acelerador financiero; Jerarquía financiera (pecking order); Costes de ajuste (demanda dinámica de factores)
A35: 3.A.35 | B35: Teorías de la demanda de dinero | C35: =COUNTA(Matriz!AK2:AK141) -> 16 | D35: Economía de Robinson Crusoe; Elección ocio-consumo (oferta de trabajo neoclásica); IS-LM; Costes de menú; Nuevo keynesiano de tres ecuaciones (NEK-2); DSGE; Modelos VAR; Renta permanente; Demanda de dinero por inventario; Dinero en la función de utilidad (MIU); Cash-in-advance (CIA); Suavización impositiva; Ramsey-Cass-Koopmans; Generaciones solapadas; Capital humano; Búsqueda monetaria
A36: 3.A.36 | B36: Política Monetaria (I) | C36: =COUNTA(Matriz!AL2:AL141) -> 3 | D36: IS-LM; Inconsistencia temporal de la política; Elección del instrumento de política monetaria
A37: 3.A.37 | B37: Política Monetaria (II) | C37: =COUNTA(Matriz!AM2:AM141) -> 8 | D37: Competencia monopolística; Contratos escalonados (rigidez nominal); Nuevo keynesiano de tres ecuaciones (NEK-2); DSGE; Modelos VAR; Renta permanente; Acelerador financiero; Suavización impositiva
A38: 3.A.38 | B38: Política Fiscal | C38: =COUNTA(Matriz!AN2:AN141) -> 8 | D38: Imposición / tarificación óptima de Ramsey; IS-LM; Nuevo keynesiano de tres ecuaciones (NEK-2); Renta permanente; Suavización impositiva; Generaciones solapadas; Modelo AK; Mundell-Fleming
A39: 3.A.39 | B39: Déficit Público | C39: =COUNTA(Matriz!AO2:AO141) -> 6 | D39: Imposición / tarificación óptima de Ramsey; Votante mediano; IS-LM; Renta permanente; Generaciones solapadas; Irrelevancia de la estructura financiera
A40: 3.A.40 | B40: Efectividad e interrelación de las Políticas Monetarias y Fiscales | C40: =COUNTA(Matriz!AP2:AP141) -> 7 | D40: Modelo keynesiano simple (renta-gasto / aspa keynesiana); IS-LM; Ciclo Real (RBC); Inconsistencia temporal de la política; Nuevo keynesiano de tres ecuaciones (NEK-2); Renta permanente; Modelo AK
A41: 3.A.41 | B41: La inflación | C41: =COUNTA(Matriz!AQ2:AQ141) -> 15 | D41: Elección ocio-consumo (oferta de trabajo neoclásica); Competencia monopolística; Contratos escalonados (rigidez nominal); Costes de menú; Nuevo keynesiano de tres ecuaciones (NEK-2); DSGE; Renta permanente; Acelerador de la inversión; Acelerador financiero; Demanda de dinero por inventario; Cash-in-advance (CIA); Hiperinflación; NAIRU / WS-PS; Factores específicos; Modelo monetario del tipo de cambio (precios flexibles)
A42: 3.A.42 | B42: Teorías de los ciclos económicos | C42: =COUNTA(Matriz!AR2:AR141) -> 18 | D42: Utilidad esperada; Competencia monopolística; Equilibrio general walrasiano / Arrow-Debreu; Oferta y demanda agregadas; Ciclo Real (RBC); Contratos escalonados (rigidez nominal); Costes de menú; Nuevo keynesiano de tres ecuaciones (NEK-2); DSGE; Modelos VAR; Modelos ARMA/ARIMA; Acelerador de la inversión; Acelerador financiero; Dinero en la función de utilidad (MIU); Ramsey-Cass-Koopmans; Modelo monetario del tipo de cambio (precios flexibles); Nueva macroeconomía de economía abierta (NOEM); Inestabilidad financiera
A43: 3.A.43 | B43: Teorías del crecimiento económico (I) | C43: =COUNTA(Matriz!AS2:AS141) -> 2 | D43: Solow-Swan; Ramsey-Cass-Koopmans
A44: 3.A.44 | B44: Teorías del crecimiento económico (I) | C44: =COUNTA(Matriz!AT2:AT141) -> 6 | D44: Competencia monopolística; Solow-Swan; Modelo AK; Capital humano; Expansión de variedades (I+D); Escalera de calidad (destrucción creadora) | E44: El main.tex se titula "Tema 3.A.43"; revisar
A45: 3.A.45 | B45: Teorías del crecimiento económico (II) | C45: =COUNTA(Matriz!AU2:AU141) -> 1 | D45: Solow-Swan
A46: 3.B.1 | B46: La información financiera de las empresas | C46: 0 | D46: — (ningún modelo del catálogo)
A47: 3.B.2 | B47: La empresa y las decisiones de inversión | C47: =COUNTA(Matriz!AV2:AV141) -> 8 | D47: Inconsistencia temporal de la política; Opciones reales de inversión; Selección de carteras media-varianza; CAPM; APT (arbitraje); Valoración de opciones; Descuento de dividendos / crecimiento constante; Irrelevancia de la estructura financiera
A48: 3.B.3 | B48: La empresa y las decisiones de financiación | C48: =COUNTA(Matriz!AW2:AW141) -> 4 | D48: Principal-agente; Ciclo vital; Irrelevancia de la estructura financiera; Jerarquía financiera (pecking order)
A49: 3.B.4 | B49: Análisis del crecimiento de la empresa | C49: =COUNTA(Matriz!AX2:AX141) -> 4 | D49: Opciones reales de inversión; CAPM; Valoración de opciones; Descuento de dividendos / crecimiento constante
A50: 3.B.5 | B50: Teoría del Comercio Internacional (I) | C50: =COUNTA(Matriz!AY2:AY141) -> 5 | D50: Modelo ricardiano; Factores específicos; Heckscher-Ohlin; Nueva teoría del comercio (rendimientos crecientes); Empresas heterogéneas
A51: 3.B.6 | B51: Teoría del Comercio Internacional (II) | C51: =COUNTA(Matriz!AZ2:AZ141) -> 6 | D51: Competencia monopolística; Modelo ricardiano; Heckscher-Ohlin; Nueva teoría del comercio (rendimientos crecientes); Empresas heterogéneas; Modelo de gravedad
A52: 3.B.7 | B52: La Política Comercial (I) | C52: =COUNTA(Matriz!BA2:BA141) -> 7 | D52: Competencia monopolística; Votante mediano; Modelo ricardiano; Nueva teoría del comercio (rendimientos crecientes); Empresas heterogéneas; Modelo de gravedad; Uniones aduaneras: creación y desviación de comercio
A53: 3.B.8 | B53: La Política Comercial (II) | C53: =COUNTA(Matriz!BB2:BB141) -> 5 | D53: Liderazgo de Stackelberg; Centro-periferia (estructuralismo); Heckscher-Ohlin; Empresas heterogéneas; Política comercial estratégica
A54: 3.B.9 | B54: Comercio internacional y crecimiento económico | C54: =COUNTA(Matriz!BC2:BC141) -> 5 | D54: Tablas input-output; Equilibrio general computable (CGE); Gran impulso (big push); Centro-periferia (estructuralismo); Empresas heterogéneas
A55: 3.B.10 | B55: Teoría de la integración económica | C55: =COUNTA(Matriz!BD2:BD141) -> 10 | D55: Competencia monopolística; Equilibrio general computable (CGE); Búsqueda y emparejamiento (DMP); Centro-periferia (estructuralismo); Nueva teoría del comercio (rendimientos crecientes); Empresas heterogéneas; Modelo de gravedad; Nueva geografía económica (centro-periferia); Uniones aduaneras: creación y desviación de comercio; Nueva macroeconomía de economía abierta (NOEM)
A56: 3.B.11 | B56: Balanza de Pagos | C56: =COUNTA(Matriz!BE2:BE141) -> 3 | D56: Nueva macroeconomía de economía abierta (NOEM); Crisis cambiarias de primera generación; Enfoque intertemporal de la cuenta corriente
A57: 3.B.12 | B57: Mecanismos de ajuste de la Balanza de Pagos | C57: =COUNTA(Matriz!BF2:BF141) -> 9 | D57: Inconsistencia temporal de la política; Nuevo keynesiano de tres ecuaciones (NEK-2); DSGE; Mecanismo flujo-especie-precio; Enfoque de elasticidades; Mundell-Fleming; Equilibrio de cartera; Nueva macroeconomía de economía abierta (NOEM); Enfoque intertemporal de la cuenta corriente | E57: El main.tex se titula "Tema 3.B.11"; revisar
A58: 3.B.13 | B58: Mercado de divisas | C58: =COUNTA(Matriz!BG2:BG141) -> 6 | D58: Utilidad esperada; Teoría prospectiva; Equilibrio de cartera; CAPM; APT (arbitraje); Chartistas y fundamentalistas (agentes heterogéneos en divisas)
A59: 3.B.14 | B59: Teorías de la determinación del Tipo de Cambio | C59: =COUNTA(Matriz!BH2:BH141) -> 15 | D59: Utilidad esperada; Análisis envolvente de datos (DEA); Modelo keynesiano simple (renta-gasto / aspa keynesiana); Modelos basados en agentes (ABM); Renta permanente; Renta relativa; Empresas heterogéneas; Mundell-Fleming; Modelo monetario del tipo de cambio (precios flexibles); Equilibrio de cartera; Efecto Balassa-Samuelson; Nueva macroeconomía de economía abierta (NOEM); CAPM; APT (arbitraje); Chartistas y fundamentalistas (agentes heterogéneos en divisas)
A60: 3.B.15 | B60: Análisis comparado de los distintos regímenes cambiarios | C60: =COUNTA(Matriz!BI2:BI141) -> 12 | D60: IS-LM; Inconsistencia temporal de la política; Modelos VAR; Modelo de gravedad; Mundell-Fleming; Modelo monetario del tipo de cambio (precios flexibles); Nueva macroeconomía de economía abierta (NOEM); Áreas monetarias óptimas; Crisis cambiarias de primera generación; Crisis cambiarias de segunda generación; Crisis cambiarias de tercera generación; Enfoque intertemporal de la cuenta corriente
A61: 3.B.16 | B61: Teoría de la integración monetaria | C61: =COUNTA(Matriz!BJ2:BJ141) -> 15 | D61: Liderazgo de Stackelberg; Mercado de limones (selección adversa); Inconsistencia temporal de la política; Elección del instrumento de política monetaria; Monopolio sindical; Solow-Swan; Nueva teoría del comercio (rendimientos crecientes); Empresas heterogéneas; Modelo de gravedad; Nueva geografía económica (centro-periferia); Modelo monetario del tipo de cambio (precios flexibles); Efecto Balassa-Samuelson; Áreas monetarias óptimas; Crisis cambiarias de primera generación; Chartistas y fundamentalistas (agentes heterogéneos en divisas)
A62: 3.B.17 | B62: Teorías explicativas de las crisis de balanza de pagos | C62: =COUNTA(Matriz!BK2:BK141) -> 9 | D62: Inconsistencia temporal de la política; Acelerador de la inversión; Nueva teoría del comercio (rendimientos crecientes); Nueva geografía económica (centro-periferia); Zona objetivo; Crisis cambiarias de primera generación; Crisis cambiarias de segunda generación; Crisis cambiarias de tercera generación; Inestabilidad financiera
A63: 3.B.18 | B63: Nueva globalización económica y financiera | C63: =COUNTA(Matriz!BL2:BL141) -> 8 | D63: Tablas input-output; Gran impulso (big push); Factores específicos; Heckscher-Ohlin; Modelo de gravedad; Uniones aduaneras: creación y desviación de comercio; Inversión extranjera y movilidad de capital; Equilibrio de cartera
A64: 3.B.19 | B64: Coordinación internacional de Políticas Económicas | C64: =COUNTA(Matriz!BM2:BM141) -> 7 | D64: IS-LM; Inconsistencia temporal de la política; Nuevo keynesiano de tres ecuaciones (NEK-2); Mundell-Fleming; Modelo monetario del tipo de cambio (precios flexibles); Nueva macroeconomía de economía abierta (NOEM); Coordinación internacional de políticas (teoría de juegos)
A65: 3.B.20 | B65: Sistema económico internacional (I) | C65: =COUNTA(Matriz!BN2:BN141) -> 3 | D65: Acelerador de la inversión; Ciclo de vida del producto; Crisis cambiarias de primera generación
A66: 3.B.21 | B66: Sistema económico internacional (II) | C66: =COUNTA(Matriz!BO2:BO141) -> 2 | D66: Modelo AK; Crisis cambiarias de primera generación
A67: 3.B.22 | B67: El Fondo Monetario Internacional | C67: =COUNTA(Matriz!BP2:BP141) -> 2 | D67: Enfoque monetario de la balanza de pagos; Programación financiera del FMI
A68: 3.B.23 | B68: Análisis de los instrumentos financieros de renta variable | C68: =COUNTA(Matriz!BQ2:BQ141) -> 5 | D68: Equilibrio de cartera; Selección de carteras media-varianza; CAPM; APT (arbitraje); Descuento de dividendos / crecimiento constante
A69: 3.B.24 | B69: Análisis de los instrumentos financieros de renta fija | C69: 0 | D69: — (ningún modelo del catálogo)
A70: 3.B.25 | B70: Análisis de los instrumentos y de los mercados de derivados | C70: =COUNTA(Matriz!BR2:BR141) -> 3 | D70: DSGE; Opciones reales de inversión; Valoración de opciones
A71: 3.B.26 | B71: Crisis financieras y pánicos bancarios | C71: =COUNTA(Matriz!BS2:BS141) -> 14 | D71: Principal-agente; Mercado de limones (selección adversa); Inconsistencia temporal de la política; Modelos ARMA/ARIMA; Modelos ARCH/GARCH; Acelerador financiero; Crisis cambiarias de primera generación; Valoración de opciones; Riesgo de crédito estructural; Irrelevancia de la estructura financiera; Estructura temporal de tipos (modelos de tipo corto); Pánicos bancarios; Racionamiento del crédito; Inestabilidad financiera
A72: 3.B.27 | B72: Regulación financiera y no-bancaria | C72: =COUNTA(Matriz!BT2:BT141) -> 7 | D72: Principal-agente; Inconsistencia temporal de la política; Modelos ARCH/GARCH; Irrelevancia de la estructura financiera; Estructura temporal de tipos (modelos de tipo corto); Pánicos bancarios; Inestabilidad financiera
A73: 3.B.28 | B73: Economía de los países en desarrollo | C73: =COUNTA(Matriz!BU2:BU141) -> 3 | D73: Imposición óptima sobre la renta; Ramsey-Cass-Koopmans; Modelo AK
A74: 3.B.29 | B74: Financiación exterior del desarrollo económico | C74: =COUNTA(Matriz!BV2:BV141) -> 5 | D74: Renta permanente; Harrod-Domar; Dos brechas; Nueva macroeconomía de economía abierta (NOEM); Enfoque intertemporal de la cuenta corriente
A75: 3.B.30 | B75: El Grupo del Banco Mundial | C75: 0 | D75: — (ningún modelo del catálogo)
A76: 3.B.31 | B76: Cambio Climático y su impacto en la economía | C76: =COUNTA(Matriz!BW2:BW141) -> 5 | D76: DSGE; Ramsey-Cass-Koopmans; Modelo monetario del tipo de cambio (precios flexibles); DICE; PAGE
A77: 3.B.32 | B77: Perspectivas económicas mundiales | C77: =COUNTA(Matriz!BX2:BX141) -> 2 | D77: Tablas input-output; Centro-periferia (estructuralismo)
A78: 3.B.33 | B78: La OMC | C78: =COUNTA(Matriz!BY2:BY141) -> 1 | D78: Inconsistencia temporal de la política
A79: 3.B.34 | B79: La OMC | C79: =COUNTA(Matriz!BZ2:BZ141) -> 1 | D79: Uniones aduaneras: creación y desviación de comercio
A80: 3.B.35 | B80: Procesos de integración no comunitarios | C80: =COUNTA(Matriz!CA2:CA141) -> 2 | D80: Gran impulso (big push); Áreas monetarias óptimas
A81: 3.B.36 | B81: Unión Europea (I) | C81: 0 | D81: — (ningún modelo del catálogo)
A82: 3.B.37 | B82: Unión Europea (II) | C82: 0 | D82: — (ningún modelo del catálogo)
A83: 3.B.38 | B83: Unión Europea (III) | C83: 0 | D83: — (ningún modelo del catálogo)
A84: 3.B.39 | B84: Unión Europea (IV): El Mercado único de la UE | C84: =COUNTA(Matriz!CB2:CB141) -> 5 | D84: Teoría de la captura del regulador; Acelerador de la inversión; Expansión de variedades (I+D); Uniones aduaneras: creación y desviación de comercio; Inversión extranjera y movilidad de capital
A85: 3.B.40 | B85: Unión Europea (V): Cohesión Económico y Social en la UE | C85: =COUNTA(Matriz!CC2:CC141) -> 1 | D85: Centro-periferia (estructuralismo)
A86: 3.B.41 | B86: Unión Europea (VI): Política Comercial de la UE | C86: 0 | D86: — (ningún modelo del catálogo)
A87: 3.B.42 | B87: Unión Europea (VII): Relaciones económicas exteriores de la UE | C87: 0 | D87: — (ningún modelo del catálogo)
A88: 3.B.43 | B88: El origen del euro | C88: =COUNTA(Matriz!CD2:CD141) -> 4 | D88: DSGE; Modelo monetario del tipo de cambio (precios flexibles); Áreas monetarias óptimas; Crisis cambiarias de segunda generación
A89: 3.B.44 | B89: Unión Bancaria | C89: 0 | D89: — (ningún modelo del catálogo)
A90: 3.B.45 | B90: La gobernanza económica de la Unión Europea y de la zona euro | C90: =COUNTA(Matriz!CE2:CE141) -> 1 | D90: Áreas monetarias óptimas
A91: 4.B.7 | B91: Teoría impositiva (I): Ingresos públicos | C91: 0 | D91: — (ningún modelo del catálogo)
A92: 4.B.8 | B92: Teoría impositiva (II): Traslación e incidencia de los impuestos en mercados competitivos y monopolistas | C92: =COUNTA(Matriz!CF2:CF141) -> 2 | D92: Incidencia impositiva en equilibrio general; Teoría neoclásica de la inversión
A93: 4.B.9 | B93: Teoría impositiva (III): Efecto renta y efecto sustitución de los impuestos | C93: =COUNTA(Matriz!CG2:CG141) -> 1 | D93: Teoría neoclásica de la inversión
A94: 4.B.10 | B94: Teoría impositiva (IV): Imposición y oferta | C94: =COUNTA(Matriz!CH2:CH141) -> 6 | D94: Mercado de limones (selección adversa); Imposición / tarificación óptima de Ramsey; Imposición óptima sobre la renta; Imposición y asunción de riesgos; Renta permanente; Imposición progresiva utilitarista (sacrificio mínimo)
A95: 4.B.11 | B95: Teoría impositiva (V): Imposición óptima | C95: =COUNTA(Matriz!CI2:CI141) -> 7 | D95: Imposición / tarificación óptima de Ramsey; Imposición óptima sobre la renta; Imposición óptima del capital (tipo cero a largo plazo); Administración tributaria óptima; Evasión fiscal; Inconsistencia temporal de la política; Imposición progresiva utilitarista (sacrificio mínimo)
A96: 4.B.12 | B96: Teoría impositiva (VI): Imposición directa | C96: =COUNTA(Matriz!CJ2:CJ141) -> 10 | D96: Mercado de limones (selección adversa); Imposición óptima sobre la renta; Imposición óptima del capital (tipo cero a largo plazo); Incidencia impositiva en equilibrio general; Votar con los pies; Teorema de la descentralización; Leviatán; Bienes públicos: provisión eficiente; Renta permanente; Imposición progresiva utilitarista (sacrificio mínimo)
A97: 4.B.13 | B97: Teoría impositiva (VII): Imposición indirecta | C97: =COUNTA(Matriz!CK2:CK141) -> 6 | D97: Tableau économique; Imposición / tarificación óptima de Ramsey; Imposición óptima sobre la renta; Imposición óptima del capital (tipo cero a largo plazo); Leviatán; Renta permanente
A98: 4.B.14 | B98: Teoría impositiva (VIII): Teoría del federalismo fiscal | C98: =COUNTA(Matriz!CL2:CL141) -> 10 | D98: Principal-agente; Votar con los pies; Teorema de la descentralización; Teoría de los clubes; Burocracia maximizadora del presupuesto; Leviatán; Votante mediano; Bienes públicos: provisión eficiente; Mundell-Fleming; Áreas monetarias óptimas
A99: 4.B.15 | B99: Empresa Pública | C99: =COUNTA(Matriz!CM2:CM141) -> 5 | D99: Mercados disputables; Principal-agente; Mercado de limones (selección adversa); Burocracia maximizadora del presupuesto; Renta permanente
A100: 4.B.16 | B100: Sistema Fiscal en España (I): Impuesto sobre la Renta de las Personas Físicas | C100: =COUNTA(Matriz!CN2:CN141) -> 2 | D100: Imposición óptima sobre la renta; Imposición óptima del capital (tipo cero a largo plazo)
...

Sheet Notas
A1: Qué contiene
A2: Resumen | B2: Una fila por modelo original: temas donde aparece él o cualquier variante suya, temas donde se desarrolla y variantes encontradas.
A3: Matriz | B3: Modelos × temas con intensidad (D/T/M). Sirve para ver qué temas comparten modelos (base para inferir relaciones).
A4: Detalle | B4: Una fila por modelo-forma-tema, con nº de menciones, epígrafe, expresiones literales y un fragmento de contexto para verificar.
A5: Temas | B5: Inventario de los 107 temas con los modelos detectados en cada uno.
A7: Método
A8: 1 | B8: Se clonaron los 107 repositorios y se extrajo el cuerpo de cada .tex (desde \begin{document}), sin comentarios LaTeX ni las entradas \MyBibItem (la plantilla repite una referencia a DAWID y GATTI en 64 temas y generaba falsos positivos).
A9: 2 | B9: Catálogo de 158 modelos originales con sus variantes, construido a partir de los nombres que el propio temario usa ("modelo de X", epígrafes, autores en mayúsculas) y del canon de la oposición. Cada forma se busca con patrones tolerantes a erratas del temario (p. ej. HECKSHER, MUNDELL-FLEMMING, ROTSCHILD-STIGLIZ, SIDRAUSKY, STACKLEBERG).
A10: 3 | B10: Los apellidos ambiguos solo cuentan con contexto de modelo, año o coautor (p. ej. "Solow" ≠ salarios de eficiencia de Solow; "Edgeworth" duopolio ≠ Edgeworth fiscal; "MIU" ≠ Mercado Interior Único; "CIA" ≠ agencia de inteligencia; "EGC" ≠ equilibrio general competitivo).
A11: 4 | B11: Intensidad: D si el modelo aparece en un epígrafe o tiene ≥5 menciones; T con 2–4; M con 1. Es una aproximación: una mención larga sin epígrafe puede ser un desarrollo real.
A13: Límites
A14: Cobertura | B14: Solo se detectan modelos del catálogo. Un modelo citado sin nombre reconocible (p. ej. "el modelo neoclásico" genérico) no aparece. Conceptos que no son modelos (curvas de Phillips/Laffer, teoremas, hipótesis de mercados eficientes) se han dejado fuera a propósito.
A15: Agrupación | B15: Original vs. variante es una decisión de criterio (p. ej. IS-LM-BP como variante de Mundell-Fleming; Galí-Monacelli dentro de NOEM; Barro-Gordon dentro de inconsistencia temporal de Kydland-Prescott). Ajustable en una segunda pasada.
A16: Contenido incompleto | B16: Varios temas tienen apartados vacíos (p. ej. 3.B.9, 3.A.45). Un modelo ausente en un tema puede deberse a que el apartado aún no está redactado.
A17: Exclusiones manuales | B17: Análisis envolvente de datos (DEA) [todas las formas] en 3.B.4; Búsqueda monetaria [todas las formas] en 3.A.15; Búsqueda y emparejamiento (DMP) [todas las formas] en 3.A.35; Chartistas y fundamentalistas (agentes heterogéneos en divisas) [todas las formas] en 3.B.36; Duopolio de Bertrand [Bertrand-Edgeworth (restricciones de capacidad)] en 3.A.3; Duopolio de Bertrand [Bertrand-Edgeworth (restricciones de capacidad)] en 3.A.16; Duopolio de Bertrand [Bertrand-Edgeworth (restricciones de capacidad)] en 4.B.10; Duopolio de Bertrand [Bertrand-Edgeworth (restricciones de capacidad)] en 4.B.11; Duopolio de Bertrand [Bertrand-Edgeworth (restricciones de capacidad)] en 4.B.12; Duopolio de Cournot [todas las formas] en 3.A.17; Enfoque intertemporal de la cuenta corriente [todas las formas] en 3.A.25; Enfoque intertemporal de la cuenta corriente [todas las formas] en 3.A.26; Imposición progresiva utilitarista (sacrificio mínimo) [todas las formas] en 3.A.19; Ramsey-Cass-Koopmans [todas las formas] en 4.B.11; Señalización en el mercado de trabajo [todas las formas] en 3.B.13; Señalización en el mercado de trabajo [todas las formas] en 3.B.15; Solow-Swan [todas las formas] en 3.A.7; Solow-Swan [todas las formas] en 3.A.27; Tablas input-output [todas las formas] en 3.A.27
A18: Modelos del catálogo sin aparición | B18: Modelo del trigo (grano) de Ricardo (Ricardo (1815)); Esquemas de reproducción de Marx (Marx (1885)); Grupos de presión (Becker (1983)); Economía dual (Lewis (1954)); Etapas del crecimiento (Rostow (1960)); Demanda representativa / solapamiento de demanda (Linder (1961)); Protección en venta (economía política) (Grossman-Helpman (1994)); Crecimiento empobrecedor (Bhagwati (1958)); Internacionalización gradual (Johanson-Vahlne (Uppsala, 1977)); Enfoque de absorción (Alexander (1952)); Economía dependiente (bienes comerciables/no comerciables) (Salter (1959) / Swan (1960)); Noise traders (De Long-Shleifer-Summers-Waldmann (1990)); Predicción de insolvencia (Z-score) (Altman (1968)); Análisis DuPont de rentabilidad (DuPont (1919)); Cinco fuerzas competitivas (Porter (1979)); Matriz producto-mercado (Ansoff (1957)); Crecimiento de la empresa (Penrose (1959)); FUND (Tol (1997))
A20: Incidencias del repositorio
A21: Repos ausentes | B21: 3.A.14; 4.B.1–4.B.6; 4.B.18; 4.B.22 (no existen en la organización).
A22: Títulos que no cuadran | B22: repo 3.A.15 → main.tex dice "Tema 3.A.9"; repo 3.A.17 → main.tex dice "Tema 3.A.16"; repo 3.A.44 → main.tex dice "Tema 3.A.43"; repo 3.B.12 → main.tex dice "Tema 3.B.11"
A23: Ficheros con otro nombre | B23: 4.B.24, 4.B.25 y 4.B.26 no tienen main.tex (usan 4_B_24.tex, etc.).
